{
  "cluster_model": "GaussianMixture",
  "cluster_n_init": 10,
  "cluster_random_state": 42,
  "features": [
    "passing",
    "receiving",
    "interrupting",
    "dribbling",
    "claiming",
    "attempted_passes_for",
    "pass_completion_percentage_for",
    "avg_vertical_distance_for",
    "avg_vertical_distance_against"
  ],
  "generated_at": "2026-05-12T00:06:07.559286+00:00",
  "league": "usl1",
  "n_clusters": 4,
  "pca_explained_variance_ratio": [
    0.4400594898332966,
    0.22609095930264084
  ],
  "season": "2021"
}