{
  "A.J. Paterson": {
    "archetype": "Progressive Carriers",
    "confidence": 0.9476960289755058,
    "position": "CB",
    "primary_metric": "Attacking Directness",
    "z_score": 0.649734816049686
  },
  "Aaron Bibout": {
    "archetype": "The Creators",
    "confidence": 0.9920365381827666,
    "position": "ST",
    "primary_metric": "Pass Quality Above Model",
    "z_score": 0.37468867425971913
  },
  "Aaron Molloy": {
    "archetype": "The Creators (2)",
    "confidence": 0.9999999999980211,
    "position": "DM",
    "primary_metric": "Chance Creation (xA/96)",
    "z_score": 1.719343497495252
  },
  "Aar\u00f3n Guill\u00e9n": {
    "archetype": "Progressive Carriers",
    "confidence": 0.9908604135830875,
    "position": "CB",
    "primary_metric": "Attacking Directness",
    "z_score": 0.9447911460707102
  },
  "Abdellatif Aboukoura": {
    "archetype": "The Creators",
    "confidence": 0.9929493833660465,
    "position": "W",
    "primary_metric": "Pass Quality Above Model",
    "z_score": 0.3235280850976044
  },
  "Abdi Mohamed": {
    "archetype": "The Finishers (2)",
    "confidence": 0.9990967833558853,
    "position": "FB",
    "primary_metric": "Shot Quality (xG/96)",
    "z_score": -0.6610239030208427
  },
  "Abdoulaye Cissoko": {
    "archetype": "Progressive Carriers",
    "confidence": 0.9996440671115953,
    "position": "CB",
    "primary_metric": "Attacking Directness",
    "z_score": 1.7196259112448427
  },
  "Abdoulaye Diop": {
    "archetype": "The Creators",
    "confidence": 0.9873769365845326,
    "position": "DM",
    "primary_metric": "Pass Quality Above Model",
    "z_score": -1.1234180929153137
  },
  "Abdul Illal Osumanu": {
    "archetype": "Progressive Carriers",
    "confidence": 0.9993583786801252,
    "position": "CB",
    "primary_metric": "Attacking Directness",
    "z_score": 1.4012811323426666
  },
  "Adrian Diz Pe": {
    "archetype": "Progressive Carriers",
    "confidence": 0.9995752451717391,
    "position": "CB",
    "primary_metric": "Attacking Directness",
    "z_score": 2.186330585474715
  },
  "Adrian Rebollar": {
    "archetype": "The Finishers (2)",
    "confidence": 0.999998716757891,
    "position": "CM",
    "primary_metric": "Shot Quality (xG/96)",
    "z_score": -0.5737227081957404
  },
  "Adrien P\u00e9rez": {
    "archetype": "The Creators (2)",
    "confidence": 0.9999999954834742,
    "position": "W",
    "primary_metric": "Chance Creation (xA/96)",
    "z_score": 2.6028220799825257
  },
  "Aedan Stanley": {
    "archetype": "The Creators (2)",
    "confidence": 0.9999922985362294,
    "position": "FB",
    "primary_metric": "Chance Creation (xA/96)",
    "z_score": 1.6691835448374777
  },
  "Aidan Rocha": {
    "archetype": "The Finishers (2)",
    "confidence": 0.9924215292805165,
    "position": "DM",
    "primary_metric": "Shot Quality (xG/96)",
    "z_score": -0.6622622644317183
  },
  "Aiden McFadden": {
    "archetype": "The Finishers (2)",
    "confidence": 0.9877825083292894,
    "position": "FB",
    "primary_metric": "Shot Quality (xG/96)",
    "z_score": -0.1834271391793126
  },
  "Akeem Ward": {
    "archetype": "The Finishers (2)",
    "confidence": 0.9303564240875837,
    "position": "FB",
    "primary_metric": "Shot Quality (xG/96)",
    "z_score": -0.6937458348116146
  },
  "Alazar Milo Yosef": {
    "archetype": "The Creators",
    "confidence": 0.6513224721599539,
    "position": "W",
    "primary_metric": "Pass Quality Above Model",
    "z_score": -1.136727892323806
  },
  "Albert Dikwa": {
    "archetype": "The Finishers",
    "confidence": 0.9999999591144162,
    "position": "ST",
    "primary_metric": "Shot Quality (xG/96)",
    "z_score": 2.190529260559015
  },
  "Aldair Sanchez": {
    "archetype": "The Finishers (2)",
    "confidence": 0.983581959478919,
    "position": "FB",
    "primary_metric": "Shot Quality (xG/96)",
    "z_score": -0.39978554016850937
  },
  "Alejandro Fuenmayor": {
    "archetype": "Progressive Carriers",
    "confidence": 0.9989704634701976,
    "position": "CB",
    "primary_metric": "Attacking Directness",
    "z_score": 1.1335159533542423
  },
  "Alejandro Lara": {
    "archetype": "Progressive Carriers",
    "confidence": 0.9974348776768484,
    "position": "CB",
    "primary_metric": "Attacking Directness",
    "z_score": 1.9193191620862389
  },
  "Alejandro Mitrano": {
    "archetype": "Progressive Carriers",
    "confidence": 0.9725486413525378,
    "position": "FB",
    "primary_metric": "Attacking Directness",
    "z_score": 0.6263943840237102
  },
  "Alex Crognale": {
    "archetype": "Progressive Carriers",
    "confidence": 0.9999999999997371,
    "position": "CB",
    "primary_metric": "Attacking Directness",
    "z_score": 1.7875678815298108
  },
  "Alex Dalou": {
    "archetype": "The Creators",
    "confidence": 0.9943755997629478,
    "position": "AM",
    "primary_metric": "Pass Quality Above Model",
    "z_score": -1.6815915194946383
  },
  "Alex Villanueva": {
    "archetype": "The Finishers (2)",
    "confidence": 0.9997863116489664,
    "position": "FB",
    "primary_metric": "Shot Quality (xG/96)",
    "z_score": -0.5865224039611684
  },
  "Alexis Souahy": {
    "archetype": "Progressive Carriers",
    "confidence": 0.9999014989897671,
    "position": "CB",
    "primary_metric": "Attacking Directness",
    "z_score": 1.6269139724512387
  },
  "Ali Coote": {
    "archetype": "The Finishers (2)",
    "confidence": 0.5984381830307745,
    "position": "W",
    "primary_metric": "Shot Quality (xG/96)",
    "z_score": -0.5091767769042294
  },
  "Allen Gavilanes": {
    "archetype": "The Creators",
    "confidence": 0.9998737755081598,
    "position": "W",
    "primary_metric": "Pass Quality Above Model",
    "z_score": -0.5454643599102696
  },
  "Amadou Dia": {
    "archetype": "The Finishers (2)",
    "confidence": 0.833978992526284,
    "position": "FB",
    "primary_metric": "Shot Quality (xG/96)",
    "z_score": -0.5776972863979524
  },
  "Amando Moreno": {
    "archetype": "The Creators",
    "confidence": 0.957107002632862,
    "position": "W",
    "primary_metric": "Pass Quality Above Model",
    "z_score": -1.3468014517535645
  },
  "Anderson Asiedu": {
    "archetype": "The Finishers (2)",
    "confidence": 0.9772456614505467,
    "position": "DM",
    "primary_metric": "Shot Quality (xG/96)",
    "z_score": -0.7545029037012146
  },
  "Andre Fortune": {
    "archetype": "The Finishers (2)",
    "confidence": 0.9568220912305374,
    "position": "DM",
    "primary_metric": "Shot Quality (xG/96)",
    "z_score": -0.8771869585281742
  },
  "Andrew Booth": {
    "archetype": "The Finishers (2)",
    "confidence": 0.9988931304449521,
    "position": "DM",
    "primary_metric": "Shot Quality (xG/96)",
    "z_score": -0.5595866107779409
  },
  "Andrew Fox": {
    "archetype": "Progressive Carriers",
    "confidence": 0.9991940323352723,
    "position": "CB",
    "primary_metric": "Attacking Directness",
    "z_score": 2.316990219989839
  },
  "Andy Cabrera": {
    "archetype": "The Creators (2)",
    "confidence": 0.9444592577385569,
    "position": "W",
    "primary_metric": "Chance Creation (xA/96)",
    "z_score": 1.329920998372794
  },
  "Anthony Herbert": {
    "archetype": "Progressive Carriers",
    "confidence": 0.9892731164611694,
    "position": "CB",
    "primary_metric": "Attacking Directness",
    "z_score": 1.7800303255303307
  },
  "Aodhan Quinn": {
    "archetype": "The Finishers (2)",
    "confidence": 0.996900597735001,
    "position": "CM",
    "primary_metric": "Shot Quality (xG/96)",
    "z_score": -0.3923255872003452
  },
  "Arthur Rogers": {
    "archetype": "The Finishers (2)",
    "confidence": 0.9999889538828197,
    "position": "FB",
    "primary_metric": "Shot Quality (xG/96)",
    "z_score": -0.9227488240203978
  },
  "Arturo Astorga": {
    "archetype": "The Finishers (2)",
    "confidence": 0.9922022633784845,
    "position": "FB",
    "primary_metric": "Shot Quality (xG/96)",
    "z_score": -0.8827139991498474
  },
  "Arturo Ordo\u00f1ez": {
    "archetype": "Progressive Carriers",
    "confidence": 0.9965875094306392,
    "position": "CB",
    "primary_metric": "Attacking Directness",
    "z_score": 2.093878562405231
  },
  "Arturo Ort\u00edz": {
    "archetype": "Progressive Carriers",
    "confidence": 0.9981718302964826,
    "position": "CB",
    "primary_metric": "Attacking Directness",
    "z_score": 2.433198540243891
  },
  "Arturo Rodriguez": {
    "archetype": "The Creators (2)",
    "confidence": 0.9999991635581348,
    "position": "AM",
    "primary_metric": "Chance Creation (xA/96)",
    "z_score": 2.706749135741793
  },
  "Ashish Chattha": {
    "archetype": "The Finishers (2)",
    "confidence": 0.9970264216714166,
    "position": "FB",
    "primary_metric": "Shot Quality (xG/96)",
    "z_score": -0.6982399643036036
  },
  "Ashton Miles": {
    "archetype": "Progressive Carriers",
    "confidence": 0.9091707454631683,
    "position": "CB",
    "primary_metric": "Attacking Directness",
    "z_score": 0.8811377852337221
  },
  "Augustine Williams": {
    "archetype": "Box Infiltrators",
    "confidence": 1.0,
    "position": "ST",
    "primary_metric": "Receiving Impact",
    "z_score": 4.621115041467619
  },
  "Avionne Flanagan": {
    "archetype": "The Creators",
    "confidence": 0.9983385663425344,
    "position": "W",
    "primary_metric": "Pass Quality Above Model",
    "z_score": -1.4018845762577286
  },
  "Babacar Diene": {
    "archetype": "The Creators (2)",
    "confidence": 0.9999921467450056,
    "position": "ST",
    "primary_metric": "Chance Creation (xA/96)",
    "z_score": 3.540766483455713
  },
  "Baboucarr Njie": {
    "archetype": "The Creators (2)",
    "confidence": 0.9830332237723041,
    "position": "FB",
    "primary_metric": "Chance Creation (xA/96)",
    "z_score": 0.7646645456442606
  },
  "Ben Bender": {
    "archetype": "The Creators (2)",
    "confidence": 0.9909216617340108,
    "position": "CM",
    "primary_metric": "Chance Creation (xA/96)",
    "z_score": 1.7951979703847833
  },
  "Ben Mines": {
    "archetype": "The Finishers (2)",
    "confidence": 0.9398688360832571,
    "position": "FB",
    "primary_metric": "Shot Quality (xG/96)",
    "z_score": -0.8049777759429253
  },
  "Ben Morris": {
    "archetype": "The Creators",
    "confidence": 0.9984335758882068,
    "position": "W",
    "primary_metric": "Pass Quality Above Model",
    "z_score": -1.948525078412566
  },
  "Ben Norris": {
    "archetype": "The Creators",
    "confidence": 0.9871289693604498,
    "position": "CM",
    "primary_metric": "Pass Quality Above Model",
    "z_score": 0.15452380595853443
  },
  "Benjamin Ofeimu": {
    "archetype": "Progressive Carriers",
    "confidence": 0.9995571956403471,
    "position": "CB",
    "primary_metric": "Attacking Directness",
    "z_score": 1.8763550928892028
  },
  "Bertin Jacquesson": {
    "archetype": "The Creators",
    "confidence": 0.9998420898300707,
    "position": "AM",
    "primary_metric": "Pass Quality Above Model",
    "z_score": -1.7115301866779726
  },
  "Beverly Makangila": {
    "archetype": "The Finishers (2)",
    "confidence": 0.9863871113650404,
    "position": "DM",
    "primary_metric": "Shot Quality (xG/96)",
    "z_score": -0.8183742970852036
  },
  "Blaine Ferri": {
    "archetype": "The Finishers (2)",
    "confidence": 0.9952977637483512,
    "position": "W",
    "primary_metric": "Shot Quality (xG/96)",
    "z_score": -0.42748365870455646
  },
  "Blake Bodily": {
    "archetype": "The Finishers (2)",
    "confidence": 0.9869324765337903,
    "position": "FB",
    "primary_metric": "Shot Quality (xG/96)",
    "z_score": -0.5297559406247513
  },
  "Boluwatife Akinyode": {
    "archetype": "Progressive Carriers",
    "confidence": 0.7025508760255106,
    "position": "CB",
    "primary_metric": "Attacking Directness",
    "z_score": -0.36539203607338644
  },
  "Boubacar Diallo": {
    "archetype": "The Finishers (2)",
    "confidence": 0.9990249017097468,
    "position": "DM",
    "primary_metric": "Shot Quality (xG/96)",
    "z_score": -0.5416827026485488
  },
  "Bradley Bourgeois": {
    "archetype": "Progressive Carriers",
    "confidence": 0.9999997233236925,
    "position": "CB",
    "primary_metric": "Attacking Directness",
    "z_score": 2.329310225313127
  },
  "Bradley Sample": {
    "archetype": "The Finishers (2)",
    "confidence": 0.9981045742201962,
    "position": "CM",
    "primary_metric": "Shot Quality (xG/96)",
    "z_score": -0.5278902091466203
  },
  "Brandan Craig": {
    "archetype": "Progressive Carriers",
    "confidence": 0.9995919884444989,
    "position": "CB",
    "primary_metric": "Attacking Directness",
    "z_score": 2.0565286728491867
  },
  "Brem Soumaoro": {
    "archetype": "The Finishers (2)",
    "confidence": 0.9804189019227642,
    "position": "CM",
    "primary_metric": "Shot Quality (xG/96)",
    "z_score": -0.9981090571506651
  },
  "Brett Levis": {
    "archetype": "The Finishers (2)",
    "confidence": 0.9922867960058445,
    "position": "FB",
    "primary_metric": "Shot Quality (xG/96)",
    "z_score": -0.8657750539159929
  },
  "Brian Iloski": {
    "archetype": "The Creators (2)",
    "confidence": 0.6124753810707736,
    "position": "W",
    "primary_metric": "Chance Creation (xA/96)",
    "z_score": 0.21385548060459728
  },
  "Brunallergene Etou": {
    "archetype": "The Creators",
    "confidence": 0.9563063031227481,
    "position": "FB",
    "primary_metric": "Pass Quality Above Model",
    "z_score": 0.10225686067430312
  },
  "Bruno Lapa": {
    "archetype": "The Creators (2)",
    "confidence": 0.9999717038287339,
    "position": "AM",
    "primary_metric": "Chance Creation (xA/96)",
    "z_score": 1.7171945842546683
  },
  "Bryan Tamacas": {
    "archetype": "The Finishers (2)",
    "confidence": 0.9552599253409814,
    "position": "FB",
    "primary_metric": "Shot Quality (xG/96)",
    "z_score": -0.23258978373693545
  },
  "Bryce Jamison": {
    "archetype": "The Finishers",
    "confidence": 0.9959022298236059,
    "position": "W",
    "primary_metric": "Shot Quality (xG/96)",
    "z_score": -0.1869701847803711
  },
  "Bryce Washington": {
    "archetype": "Progressive Carriers",
    "confidence": 0.9832453160477492,
    "position": "CB",
    "primary_metric": "Attacking Directness",
    "z_score": 0.5561651553664861
  },
  "Bura": {
    "archetype": "Progressive Carriers",
    "confidence": 0.6498066885240289,
    "position": "CM",
    "primary_metric": "Attacking Directness",
    "z_score": 0.462075663235046
  },
  "Cal Jennings": {
    "archetype": "Box Infiltrators",
    "confidence": 1.0,
    "position": "AM",
    "primary_metric": "Receiving Impact",
    "z_score": 7.91893110157847
  },
  "Callum Chapman-Page": {
    "archetype": "The Finishers (2)",
    "confidence": 0.9875697890065395,
    "position": "CB",
    "primary_metric": "Shot Quality (xG/96)",
    "z_score": -0.6957574207479794
  },
  "Camden Riley": {
    "archetype": "The Finishers (2)",
    "confidence": 0.9754494729247796,
    "position": "CB",
    "primary_metric": "Shot Quality (xG/96)",
    "z_score": -0.29680659078222876
  },
  "Cameron Dunbar": {
    "archetype": "The Creators",
    "confidence": 0.9630498363805324,
    "position": "W",
    "primary_metric": "Pass Quality Above Model",
    "z_score": 0.014284785994493631
  },
  "Cameron Lindley": {
    "archetype": "The Creators (2)",
    "confidence": 0.9996413868950373,
    "position": "CM",
    "primary_metric": "Chance Creation (xA/96)",
    "z_score": 0.6926948235860286
  },
  "Camilo Ponce": {
    "archetype": "The Creators",
    "confidence": 0.9997676064733512,
    "position": "W",
    "primary_metric": "Pass Quality Above Model",
    "z_score": -2.186458696553804
  },
  "Carlos Guzm\u00e1n": {
    "archetype": "The Finishers (2)",
    "confidence": 0.9999711098338904,
    "position": "CB",
    "primary_metric": "Shot Quality (xG/96)",
    "z_score": -0.5752870552742592
  },
  "Carson Vom Steeg": {
    "archetype": "Progressive Carriers",
    "confidence": 0.9760978102757583,
    "position": "CB",
    "primary_metric": "Attacking Directness",
    "z_score": 1.1128526532867022
  },
  "Carter Manley": {
    "archetype": "Progressive Carriers",
    "confidence": 0.989484212620973,
    "position": "CB",
    "primary_metric": "Attacking Directness",
    "z_score": 2.079635180723455
  },
  "Charlie Adams": {
    "archetype": "The Finishers (2)",
    "confidence": 0.9967660600058093,
    "position": "DM",
    "primary_metric": "Shot Quality (xG/96)",
    "z_score": -0.7481159551432696
  },
  "Charlie Dennis": {
    "archetype": "The Creators (2)",
    "confidence": 0.9092238449031634,
    "position": "CM",
    "primary_metric": "Chance Creation (xA/96)",
    "z_score": 2.0635316941549124
  },
  "Chase Boone": {
    "archetype": "The Creators",
    "confidence": 0.9509349745279506,
    "position": "W",
    "primary_metric": "Pass Quality Above Model",
    "z_score": -0.6702479201077737
  },
  "Chibuike Ukaegbu": {
    "archetype": "The Finishers (2)",
    "confidence": 0.830047225185729,
    "position": "CB",
    "primary_metric": "Shot Quality (xG/96)",
    "z_score": -0.8801612413831025
  },
  "Chris Allan": {
    "archetype": "The Finishers (2)",
    "confidence": 0.9994907237441387,
    "position": "DM",
    "primary_metric": "Shot Quality (xG/96)",
    "z_score": -0.7596869377771358
  },
  "Christian Pinzon": {
    "archetype": "The Creators (2)",
    "confidence": 0.7463727775512444,
    "position": "W",
    "primary_metric": "Chance Creation (xA/96)",
    "z_score": 0.6968078622670036
  },
  "Christian Sorto": {
    "archetype": "The Creators",
    "confidence": 0.9856439378916155,
    "position": "CM",
    "primary_metric": "Pass Quality Above Model",
    "z_score": -0.6949565401683757
  },
  "Christiano Fran\u00e7ois": {
    "archetype": "The Creators (2)",
    "confidence": 0.9863815190778118,
    "position": "ST",
    "primary_metric": "Chance Creation (xA/96)",
    "z_score": 2.3581808618629587
  },
  "Christopher Gloster": {
    "archetype": "The Finishers (2)",
    "confidence": 0.9997626124228581,
    "position": "FB",
    "primary_metric": "Shot Quality (xG/96)",
    "z_score": -0.900633186868594
  },
  "Christopher Hegardt": {
    "archetype": "The Creators (2)",
    "confidence": 0.9531997524309936,
    "position": "W",
    "primary_metric": "Chance Creation (xA/96)",
    "z_score": 1.768536610133086
  },
  "Clay Holstad": {
    "archetype": "The Finishers (2)",
    "confidence": 0.9732420068445466,
    "position": "CM",
    "primary_metric": "Shot Quality (xG/96)",
    "z_score": -0.48154378677256765
  },
  "Coleman Gannon": {
    "archetype": "The Creators",
    "confidence": 0.973502495713113,
    "position": "W",
    "primary_metric": "Pass Quality Above Model",
    "z_score": 0.010261672823160877
  },
  "Collin Martin": {
    "archetype": "The Finishers (2)",
    "confidence": 0.992391932068934,
    "position": "CM",
    "primary_metric": "Shot Quality (xG/96)",
    "z_score": -0.5288384782412057
  },
  "Collin Smith": {
    "archetype": "The Creators",
    "confidence": 0.9957554822830184,
    "position": "FB",
    "primary_metric": "Pass Quality Above Model",
    "z_score": -1.563446096029833
  },
  "Connor Rutz": {
    "archetype": "The Finishers",
    "confidence": 0.9929245300038285,
    "position": "W",
    "primary_metric": "Shot Quality (xG/96)",
    "z_score": 1.4237391891879885
  },
  "Conor Donovan": {
    "archetype": "Progressive Carriers",
    "confidence": 0.9893429631455223,
    "position": "CB",
    "primary_metric": "Attacking Directness",
    "z_score": 1.4033864497080382
  },
  "Conor McGlynn": {
    "archetype": "The Finishers (2)",
    "confidence": 0.9928346489102269,
    "position": "CM",
    "primary_metric": "Shot Quality (xG/96)",
    "z_score": -0.16974202714578707
  },
  "Cristian Parano": {
    "archetype": "The Creators (2)",
    "confidence": 0.9989211258147062,
    "position": "W",
    "primary_metric": "Chance Creation (xA/96)",
    "z_score": 1.5475919755728615
  },
  "Daltyn Knutson": {
    "archetype": "Progressive Carriers",
    "confidence": 0.9999996568418992,
    "position": "CB",
    "primary_metric": "Attacking Directness",
    "z_score": 1.1178690267622182
  },
  "Damia Viader I Masdeu": {
    "archetype": "The Finishers (2)",
    "confidence": 0.704096349683618,
    "position": "FB",
    "primary_metric": "Shot Quality (xG/96)",
    "z_score": -0.4152818931359587
  },
  "Damian Rivera": {
    "archetype": "The Creators (2)",
    "confidence": 0.999999997566789,
    "position": "AM",
    "primary_metric": "Chance Creation (xA/96)",
    "z_score": 3.0218422310621236
  },
  "Daniel Barbir": {
    "archetype": "Progressive Carriers",
    "confidence": 0.9563372337537477,
    "position": "CB",
    "primary_metric": "Attacking Directness",
    "z_score": 1.3004598229565185
  },
  "Daniel Bruce": {
    "archetype": "The Creators",
    "confidence": 0.9997423849872059,
    "position": "ST",
    "primary_metric": "Pass Quality Above Model",
    "z_score": -0.9055665146876452
  },
  "Daniel Crisostomo": {
    "archetype": "The Finishers (2)",
    "confidence": 0.9936152817810431,
    "position": "CM",
    "primary_metric": "Shot Quality (xG/96)",
    "z_score": -0.38573376342535637
  },
  "Daniel Griffin": {
    "archetype": "The Creators",
    "confidence": 0.9553194678784961,
    "position": "CM",
    "primary_metric": "Pass Quality Above Model",
    "z_score": 0.06943496238484675
  },
  "Daniel G\u00f3mez": {
    "archetype": "The Finishers (2)",
    "confidence": 0.7824333801431368,
    "position": "CM",
    "primary_metric": "Shot Quality (xG/96)",
    "z_score": -0.8676662947636212
  },
  "Daniel Rovira": {
    "archetype": "The Finishers (2)",
    "confidence": 0.9946220191338583,
    "position": "FB",
    "primary_metric": "Shot Quality (xG/96)",
    "z_score": -0.9522247963661828
  },
  "Danny Barrera": {
    "archetype": "The Creators (2)",
    "confidence": 0.9989303210275113,
    "position": "AM",
    "primary_metric": "Chance Creation (xA/96)",
    "z_score": 3.2580705635099005
  },
  "Dariusz Formella": {
    "archetype": "The Creators",
    "confidence": 0.9581892620107445,
    "position": "ST",
    "primary_metric": "Pass Quality Above Model",
    "z_score": -0.4680194313621141
  },
  "Dawson McCartney": {
    "archetype": "The Finishers (2)",
    "confidence": 0.9706355456504419,
    "position": "CM",
    "primary_metric": "Shot Quality (xG/96)",
    "z_score": 0.03784197303472334
  },
  "Dayonn Harris": {
    "archetype": "The Creators",
    "confidence": 0.9986123817953841,
    "position": "W",
    "primary_metric": "Pass Quality Above Model",
    "z_score": -1.837554206769971
  },
  "Delentz Pierre": {
    "archetype": "Progressive Carriers",
    "confidence": 0.9999992454970097,
    "position": "CB",
    "primary_metric": "Attacking Directness",
    "z_score": 2.207461733845671
  },
  "Derek Dodson": {
    "archetype": "The Finishers (2)",
    "confidence": 0.5582916057879239,
    "position": "FB",
    "primary_metric": "Shot Quality (xG/96)",
    "z_score": -0.38337082052617477
  },
  "Deshane Beckford": {
    "archetype": "The Creators",
    "confidence": 0.5017833221044729,
    "position": "W",
    "primary_metric": "Pass Quality Above Model",
    "z_score": -0.7713621644806036
  },
  "Devon Amoo-Mensah": {
    "archetype": "Progressive Carriers",
    "confidence": 0.9769407638544961,
    "position": "CB",
    "primary_metric": "Attacking Directness",
    "z_score": 1.1928287215984266
  },
  "Diba Nwegbo": {
    "archetype": "The Creators (2)",
    "confidence": 0.849980978320303,
    "position": "W",
    "primary_metric": "Chance Creation (xA/96)",
    "z_score": 0.6084519045957781
  },
  "Diego Guti\u00e9rrez": {
    "archetype": "The Creators",
    "confidence": 0.9996764265659716,
    "position": "W",
    "primary_metric": "Pass Quality Above Model",
    "z_score": -0.883439392245315
  },
  "Dieng Mamadou": {
    "archetype": "Box Infiltrators",
    "confidence": 1.0,
    "position": "ST",
    "primary_metric": "Receiving Impact",
    "z_score": 5.555751252756893
  },
  "Dillon Powers": {
    "archetype": "Progressive Carriers",
    "confidence": 0.9985894305773919,
    "position": "CB",
    "primary_metric": "Attacking Directness",
    "z_score": 1.2679963490139303
  },
  "Diogo Pacheco": {
    "archetype": "The Creators",
    "confidence": 0.9992269069998727,
    "position": "W",
    "primary_metric": "Pass Quality Above Model",
    "z_score": -1.4200891633580095
  },
  "Dom Dwyer": {
    "archetype": "The Creators",
    "confidence": 0.9999999999997691,
    "position": "ST",
    "primary_metric": "Pass Quality Above Model",
    "z_score": -3.614160983230514
  },
  "Dominick Hernandez": {
    "archetype": "The Finishers (2)",
    "confidence": 0.9863296913146209,
    "position": "AM",
    "primary_metric": "Shot Quality (xG/96)",
    "z_score": -0.44135419449061597
  },
  "Douglas Mart\u00ednez": {
    "archetype": "The Creators (2)",
    "confidence": 0.9994804295776974,
    "position": "W",
    "primary_metric": "Chance Creation (xA/96)",
    "z_score": 1.6241443045777182
  },
  "Drew Skundrich": {
    "archetype": "The Finishers (2)",
    "confidence": 0.9928968812257692,
    "position": "CM",
    "primary_metric": "Shot Quality (xG/96)",
    "z_score": -0.4997371676725267
  },
  "Duke Lacroix": {
    "archetype": "Progressive Carriers",
    "confidence": 0.9997022508035965,
    "position": "CB",
    "primary_metric": "Attacking Directness",
    "z_score": 0.7947937816810582
  },
  "Dylan Borczak": {
    "archetype": "The Creators",
    "confidence": 0.9915419391074305,
    "position": "W",
    "primary_metric": "Pass Quality Above Model",
    "z_score": 0.48800636191892494
  },
  "Edgardo Rito": {
    "archetype": "The Creators",
    "confidence": 0.492519854169467,
    "position": "W",
    "primary_metric": "Pass Quality Above Model",
    "z_score": -0.13725247679237323
  },
  "Edison Azcona": {
    "archetype": "The Finishers (2)",
    "confidence": 0.8857124052141069,
    "position": "ST",
    "primary_metric": "Shot Quality (xG/96)",
    "z_score": -0.2089288141604835
  },
  "Edward Kizza": {
    "archetype": "The Finishers",
    "confidence": 0.999999999846322,
    "position": "ST",
    "primary_metric": "Shot Quality (xG/96)",
    "z_score": 1.8360665384086305
  },
  "Edwin Laszo": {
    "archetype": "The Finishers (2)",
    "confidence": 0.9781217574301391,
    "position": "DM",
    "primary_metric": "Shot Quality (xG/96)",
    "z_score": -0.8085635048962089
  },
  "Edwin Munjoma": {
    "archetype": "The Finishers (2)",
    "confidence": 0.9874378410824257,
    "position": "FB",
    "primary_metric": "Shot Quality (xG/96)",
    "z_score": -0.6596602882218352
  },
  "Elijah Wynder": {
    "archetype": "The Finishers (2)",
    "confidence": 0.9778902772665476,
    "position": "CM",
    "primary_metric": "Shot Quality (xG/96)",
    "z_score": -0.3330978040191783
  },
  "Elliot Collier": {
    "archetype": "The Creators",
    "confidence": 0.9999777688721236,
    "position": "W",
    "primary_metric": "Pass Quality Above Model",
    "z_score": -1.6145396333057591
  },
  "Elvis Amoh": {
    "archetype": "The Creators",
    "confidence": 0.9999999988603889,
    "position": "ST",
    "primary_metric": "Pass Quality Above Model",
    "z_score": -2.277314002339735
  },
  "Emerson Hyndman": {
    "archetype": "The Finishers (2)",
    "confidence": 0.9926052695197012,
    "position": "DM",
    "primary_metric": "Shot Quality (xG/96)",
    "z_score": -0.300205139804904
  },
  "Emil Cuello": {
    "archetype": "The Finishers (2)",
    "confidence": 0.9999786819602658,
    "position": "FB",
    "primary_metric": "Shot Quality (xG/96)",
    "z_score": -0.2870392925116723
  },
  "Emilio Ycaza": {
    "archetype": "The Creators",
    "confidence": 0.9650599053722632,
    "position": "AM",
    "primary_metric": "Pass Quality Above Model",
    "z_score": 0.11439325207449023
  },
  "Emmanuel Johnson": {
    "archetype": "The Creators",
    "confidence": 0.9998493178417543,
    "position": "ST",
    "primary_metric": "Pass Quality Above Model",
    "z_score": -2.492785238607698
  },
  "Emmanuel Samadia": {
    "archetype": "The Creators (2)",
    "confidence": 0.6384342228044386,
    "position": "FB",
    "primary_metric": "Chance Creation (xA/96)",
    "z_score": 1.3410587018037918
  },
  "Emrah Klimenta": {
    "archetype": "Progressive Carriers",
    "confidence": 0.9999997081633722,
    "position": "CB",
    "primary_metric": "Attacking Directness",
    "z_score": 1.9621012902763908
  },
  "Enzo Martinez": {
    "archetype": "The Finishers (2)",
    "confidence": 0.9979105755917423,
    "position": "CM",
    "primary_metric": "Shot Quality (xG/96)",
    "z_score": 0.4237065607735214
  },
  "Eric Calvillo": {
    "archetype": "The Creators (2)",
    "confidence": 0.9998529975618394,
    "position": "CM",
    "primary_metric": "Chance Creation (xA/96)",
    "z_score": 0.08626121683624695
  },
  "Erickson Gallardo": {
    "archetype": "The Creators",
    "confidence": 0.8107119445708943,
    "position": "W",
    "primary_metric": "Pass Quality Above Model",
    "z_score": -0.6152318474897984
  },
  "Ethan Zubak": {
    "archetype": "The Finishers",
    "confidence": 0.9999998348216342,
    "position": "ST",
    "primary_metric": "Shot Quality (xG/96)",
    "z_score": 1.3037459536099627
  },
  "Etsgar Cruz": {
    "archetype": "The Creators",
    "confidence": 0.998772842500944,
    "position": "W",
    "primary_metric": "Pass Quality Above Model",
    "z_score": -1.6570505291495081
  },
  "Evan Conway": {
    "archetype": "The Creators",
    "confidence": 0.9999943897988062,
    "position": "AM",
    "primary_metric": "Pass Quality Above Model",
    "z_score": -1.2129323609774671
  },
  "Ezra Armstrong": {
    "archetype": "The Finishers (2)",
    "confidence": 0.9999530018327242,
    "position": "FB",
    "primary_metric": "Shot Quality (xG/96)",
    "z_score": -0.5638945332355229
  },
  "Fabien Garcia": {
    "archetype": "Progressive Carriers",
    "confidence": 0.9074451584120456,
    "position": "CB",
    "primary_metric": "Attacking Directness",
    "z_score": 0.9098324811765701
  },
  "Faysal Bettache": {
    "archetype": "The Finishers (2)",
    "confidence": 0.9922432992162658,
    "position": "W",
    "primary_metric": "Shot Quality (xG/96)",
    "z_score": -0.7181428828831573
  },
  "Fede Varela": {
    "archetype": "The Finishers (2)",
    "confidence": 0.5616975251606265,
    "position": "AM",
    "primary_metric": "Shot Quality (xG/96)",
    "z_score": 0.06884810416566174
  },
  "Florian Valot": {
    "archetype": "The Finishers (2)",
    "confidence": 0.9972237837291167,
    "position": "W",
    "primary_metric": "Shot Quality (xG/96)",
    "z_score": 0.05218717886653373
  },
  "Forrest Lasso": {
    "archetype": "The Finishers (2)",
    "confidence": 0.9993554180255159,
    "position": "CB",
    "primary_metric": "Shot Quality (xG/96)",
    "z_score": 0.14058738287142766
  },
  "Francisco Nevarez": {
    "archetype": "The Finishers (2)",
    "confidence": 0.9999702461361812,
    "position": "CM",
    "primary_metric": "Shot Quality (xG/96)",
    "z_score": -0.6350275618020824
  },
  "Frank L\u00f3pez": {
    "archetype": "The Creators",
    "confidence": 0.9999999442332184,
    "position": "ST",
    "primary_metric": "Pass Quality Above Model",
    "z_score": -1.870342579116333
  },
  "Frank Nodarse": {
    "archetype": "The Finishers (2)",
    "confidence": 0.9999171647945343,
    "position": "CB",
    "primary_metric": "Shot Quality (xG/96)",
    "z_score": -0.32534552835127345
  },
  "Frederik Kleemann": {
    "archetype": "Progressive Carriers",
    "confidence": 0.9999929287344582,
    "position": "CB",
    "primary_metric": "Attacking Directness",
    "z_score": 1.9176557014518705
  },
  "Gabriel Alves": {
    "archetype": "The Finishers (2)",
    "confidence": 0.9227083987979757,
    "position": "FB",
    "primary_metric": "Shot Quality (xG/96)",
    "z_score": -0.8271995495416371
  },
  "Gabriel Torres": {
    "archetype": "The Creators (2)",
    "confidence": 0.6172386482197963,
    "position": "FB",
    "primary_metric": "Chance Creation (xA/96)",
    "z_score": 1.3153529960788723
  },
  "Gabriel de Freitas": {
    "archetype": "The Finishers (2)",
    "confidence": 0.9994722397360718,
    "position": "CM",
    "primary_metric": "Shot Quality (xG/96)",
    "z_score": -0.6753818082694638
  },
  "Gagi Margvelashvili": {
    "archetype": "Progressive Carriers",
    "confidence": 0.9925137305283919,
    "position": "CB",
    "primary_metric": "Attacking Directness",
    "z_score": 1.7776131092960143
  },
  "Gaoussou Samake": {
    "archetype": "The Creators",
    "confidence": 0.7032830351324357,
    "position": "W",
    "primary_metric": "Pass Quality Above Model",
    "z_score": -0.9993050515796982
  },
  "Gennaro Michael Nigro": {
    "archetype": "Progressive Carriers",
    "confidence": 0.9999463971155992,
    "position": "FB",
    "primary_metric": "Attacking Directness",
    "z_score": 0.528484130747706
  },
  "Giulio Doratiotto": {
    "archetype": "The Finishers (2)",
    "confidence": 0.9279822835585252,
    "position": "CM",
    "primary_metric": "Shot Quality (xG/96)",
    "z_score": -0.5071230751017072
  },
  "Graham Smith": {
    "archetype": "Progressive Carriers",
    "confidence": 0.9998150468441027,
    "position": "CB",
    "primary_metric": "Attacking Directness",
    "z_score": 1.5789335297786868
  },
  "Grant Robinson": {
    "archetype": "The Finishers (2)",
    "confidence": 0.9997592883578389,
    "position": "FB",
    "primary_metric": "Shot Quality (xG/96)",
    "z_score": -0.8009579297052382
  },
  "Grant Stoneman": {
    "archetype": "Progressive Carriers",
    "confidence": 0.9704599954276012,
    "position": "CB",
    "primary_metric": "Attacking Directness",
    "z_score": 1.4853118859506624
  },
  "Grayson Doody": {
    "archetype": "The Finishers (2)",
    "confidence": 0.7882058873188029,
    "position": "FB",
    "primary_metric": "Shot Quality (xG/96)",
    "z_score": -0.5381468838633825
  },
  "Greg Hurst": {
    "archetype": "The Creators",
    "confidence": 0.999999948179846,
    "position": "ST",
    "primary_metric": "Pass Quality Above Model",
    "z_score": -1.4271296114078418
  },
  "Guillermo Diaz": {
    "archetype": "The Creators (2)",
    "confidence": 0.9818171583992112,
    "position": "FB",
    "primary_metric": "Chance Creation (xA/96)",
    "z_score": 2.73759107377797
  },
  "Harry Swartz": {
    "archetype": "The Creators",
    "confidence": 0.9606239447588395,
    "position": "W",
    "primary_metric": "Pass Quality Above Model",
    "z_score": -0.33425091841530025
  },
  "Harvey St. Clair": {
    "archetype": "The Finishers (2)",
    "confidence": 0.9999995196061419,
    "position": "FB",
    "primary_metric": "Shot Quality (xG/96)",
    "z_score": -0.9680915384364353
  },
  "Hayden White": {
    "archetype": "The Finishers (2)",
    "confidence": 0.9419186006979174,
    "position": "FB",
    "primary_metric": "Shot Quality (xG/96)",
    "z_score": -1.017305601702045
  },
  "Houssou Landru": {
    "archetype": "The Creators (2)",
    "confidence": 0.6199886604665293,
    "position": "DM",
    "primary_metric": "Chance Creation (xA/96)",
    "z_score": 0.25433828582773904
  },
  "Hugh Alexander Dixon": {
    "archetype": "The Creators",
    "confidence": 0.9964679481115933,
    "position": "W",
    "primary_metric": "Pass Quality Above Model",
    "z_score": -0.5215938884270286
  },
  "Hugo Mbongue": {
    "archetype": "The Creators",
    "confidence": 0.9999999688176158,
    "position": "ST",
    "primary_metric": "Pass Quality Above Model",
    "z_score": -2.040017377117292
  },
  "Ilya Alekseev": {
    "archetype": "The Creators",
    "confidence": 0.997440632817875,
    "position": "FB",
    "primary_metric": "Pass Quality Above Model",
    "z_score": 0.21319420637380368
  },
  "Irakoze Donasiyano": {
    "archetype": "The Finishers (2)",
    "confidence": 0.9998090935136225,
    "position": "CM",
    "primary_metric": "Shot Quality (xG/96)",
    "z_score": -0.6675762197822497
  },
  "Isaiah Johnston": {
    "archetype": "The Finishers (2)",
    "confidence": 0.9975671463388321,
    "position": "CM",
    "primary_metric": "Shot Quality (xG/96)",
    "z_score": -0.8077219995033066
  },
  "J.C. Ngando": {
    "archetype": "The Creators (2)",
    "confidence": 0.9999999999999112,
    "position": "DM",
    "primary_metric": "Chance Creation (xA/96)",
    "z_score": 1.982252620608112
  },
  "J.J. Williams": {
    "archetype": "The Creators",
    "confidence": 0.9999999998506865,
    "position": "ST",
    "primary_metric": "Pass Quality Above Model",
    "z_score": -2.1129027774046034
  },
  "Jack Blake": {
    "archetype": "The Creators (2)",
    "confidence": 0.9999998731817543,
    "position": "W",
    "primary_metric": "Chance Creation (xA/96)",
    "z_score": 0.9731483989983337
  },
  "Jack Gurr": {
    "archetype": "The Creators (2)",
    "confidence": 0.9957959276788426,
    "position": "FB",
    "primary_metric": "Chance Creation (xA/96)",
    "z_score": 2.7409162425431415
  },
  "Jack Panayotou": {
    "archetype": "The Creators (2)",
    "confidence": 0.999859062748445,
    "position": "AM",
    "primary_metric": "Chance Creation (xA/96)",
    "z_score": 3.211459143991341
  },
  "Jackson Conway": {
    "archetype": "The Finishers",
    "confidence": 0.9770265533718232,
    "position": "ST",
    "primary_metric": "Shot Quality (xG/96)",
    "z_score": 1.1201143588602143
  },
  "Jackson Walti": {
    "archetype": "The Finishers (2)",
    "confidence": 0.8007360961495239,
    "position": "CM",
    "primary_metric": "Shot Quality (xG/96)",
    "z_score": -0.7417889704842889
  },
  "Jacob Erlandson": {
    "archetype": "Progressive Carriers",
    "confidence": 0.9991979111221665,
    "position": "CB",
    "primary_metric": "Attacking Directness",
    "z_score": 1.0418176858847064
  },
  "Jacob Rufe": {
    "archetype": "The Finishers (2)",
    "confidence": 0.7336460233593932,
    "position": "CM",
    "primary_metric": "Shot Quality (xG/96)",
    "z_score": -0.6590601173163865
  },
  "Jacobo Reyes": {
    "archetype": "The Creators (2)",
    "confidence": 0.9999729380904353,
    "position": "W",
    "primary_metric": "Chance Creation (xA/96)",
    "z_score": 2.7155360523495418
  },
  "Jairo Henriquez": {
    "archetype": "The Finishers (2)",
    "confidence": 0.9296259056374998,
    "position": "W",
    "primary_metric": "Shot Quality (xG/96)",
    "z_score": 0.08580473926197253
  },
  "Jake LaCava": {
    "archetype": "The Creators",
    "confidence": 0.999999999992113,
    "position": "ST",
    "primary_metric": "Pass Quality Above Model",
    "z_score": -3.179329501295632
  },
  "Jake Morris": {
    "archetype": "The Creators",
    "confidence": 0.9913477325807688,
    "position": "FB",
    "primary_metric": "Pass Quality Above Model",
    "z_score": -0.4423385589517735
  },
  "James Murphy": {
    "archetype": "Progressive Carriers",
    "confidence": 0.7113655050115975,
    "position": "DM",
    "primary_metric": "Attacking Directness",
    "z_score": 0.29910850421180574
  },
  "James Musa": {
    "archetype": "Progressive Carriers",
    "confidence": 0.9999823250908753,
    "position": "CB",
    "primary_metric": "Attacking Directness",
    "z_score": 2.249646055870347
  },
  "Jansen Wilson": {
    "archetype": "The Creators",
    "confidence": 0.8406405848831907,
    "position": "FB",
    "primary_metric": "Pass Quality Above Model",
    "z_score": 0.10255859416215307
  },
  "Jared Trimmer": {
    "archetype": "Progressive Carriers",
    "confidence": 0.999989192739591,
    "position": "CB",
    "primary_metric": "Attacking Directness",
    "z_score": 1.5185031239207862
  },
  "Jay Chapman": {
    "archetype": "The Finishers (2)",
    "confidence": 0.999466264465182,
    "position": "DM",
    "primary_metric": "Shot Quality (xG/96)",
    "z_score": -0.7068793087000028
  },
  "Jearl Margaritha": {
    "archetype": "The Creators (2)",
    "confidence": 0.989091171007705,
    "position": "W",
    "primary_metric": "Chance Creation (xA/96)",
    "z_score": 2.006989672882645
  },
  "Jeciel Cedeno": {
    "archetype": "The Creators",
    "confidence": 0.9977625823732397,
    "position": "W",
    "primary_metric": "Pass Quality Above Model",
    "z_score": -1.5475547990030685
  },
  "Jerry Ayon": {
    "archetype": "The Finishers (2)",
    "confidence": 0.9347273399156629,
    "position": "DM",
    "primary_metric": "Shot Quality (xG/96)",
    "z_score": -0.335342409254623
  },
  "Jes\u00fas Enr\u00edquez": {
    "archetype": "The Creators (2)",
    "confidence": 0.6468307984692226,
    "position": "W",
    "primary_metric": "Chance Creation (xA/96)",
    "z_score": 1.1900534558977227
  },
  "Joaquin Rivas": {
    "archetype": "The Creators (2)",
    "confidence": 0.6860892987863303,
    "position": "ST",
    "primary_metric": "Chance Creation (xA/96)",
    "z_score": 0.1901905394325622
  },
  "Joe Gyau": {
    "archetype": "The Creators (2)",
    "confidence": 0.9743415316768491,
    "position": "W",
    "primary_metric": "Chance Creation (xA/96)",
    "z_score": 1.2378967320920353
  },
  "Joe Hafferty": {
    "archetype": "Progressive Carriers",
    "confidence": 0.9988578505528996,
    "position": "CB",
    "primary_metric": "Attacking Directness",
    "z_score": 1.080441162488938
  },
  "Joey Akpunonu": {
    "archetype": "The Finishers (2)",
    "confidence": 0.9999919293303922,
    "position": "CB",
    "primary_metric": "Shot Quality (xG/96)",
    "z_score": -0.8530224416485522
  },
  "Joey Dezart": {
    "archetype": "The Finishers (2)",
    "confidence": 0.9952918788461398,
    "position": "CM",
    "primary_metric": "Shot Quality (xG/96)",
    "z_score": -0.9092253464005686
  },
  "John Scearce": {
    "archetype": "The Finishers (2)",
    "confidence": 0.9671923807124028,
    "position": "DM",
    "primary_metric": "Shot Quality (xG/96)",
    "z_score": -0.714251388524244
  },
  "John Stenberg": {
    "archetype": "Progressive Carriers",
    "confidence": 0.9964069635616419,
    "position": "CB",
    "primary_metric": "Attacking Directness",
    "z_score": 1.7606146209385667
  },
  "Johnny Rodriguez": {
    "archetype": "The Finishers",
    "confidence": 0.9994111705237892,
    "position": "ST",
    "primary_metric": "Shot Quality (xG/96)",
    "z_score": 2.4970233567104883
  },
  "Jojea Kwizera": {
    "archetype": "The Creators (2)",
    "confidence": 0.9999964064134924,
    "position": "FB",
    "primary_metric": "Chance Creation (xA/96)",
    "z_score": 2.4168163145999855
  },
  "Jon Bakero": {
    "archetype": "The Creators (2)",
    "confidence": 0.6429998604397302,
    "position": "ST",
    "primary_metric": "Chance Creation (xA/96)",
    "z_score": 0.9564675558646395
  },
  "Jon-Talen Maples": {
    "archetype": "Progressive Carriers",
    "confidence": 0.9998263415265364,
    "position": "CB",
    "primary_metric": "Attacking Directness",
    "z_score": 1.2479568466842785
  },
  "Jonas Fjeldberg": {
    "archetype": "The Creators (2)",
    "confidence": 0.9968981118998047,
    "position": "W",
    "primary_metric": "Chance Creation (xA/96)",
    "z_score": 2.199023137224964
  },
  "Jonathan Ricketts": {
    "archetype": "The Creators",
    "confidence": 0.9988168730588421,
    "position": "FB",
    "primary_metric": "Pass Quality Above Model",
    "z_score": -0.9929015964486603
  },
  "Jordan Ayimbila": {
    "archetype": "The Creators",
    "confidence": 0.6711146381851011,
    "position": "FB",
    "primary_metric": "Pass Quality Above Model",
    "z_score": -1.480167653383245
  },
  "Jordan Doherty": {
    "archetype": "Progressive Carriers",
    "confidence": 0.9999999999686988,
    "position": "CB",
    "primary_metric": "Attacking Directness",
    "z_score": 1.6851350946541188
  },
  "Jordan Scarlett": {
    "archetype": "Progressive Carriers",
    "confidence": 0.9914352853172107,
    "position": "CB",
    "primary_metric": "Attacking Directness",
    "z_score": 1.4639468134279985
  },
  "Jorge Gonzalez Asensi": {
    "archetype": "The Creators",
    "confidence": 0.9999999673332353,
    "position": "W",
    "primary_metric": "Pass Quality Above Model",
    "z_score": -0.9573305708254599
  },
  "Jorge Hern\u00e1ndez": {
    "archetype": "The Creators (2)",
    "confidence": 0.999986923167435,
    "position": "CM",
    "primary_metric": "Chance Creation (xA/96)",
    "z_score": 2.595418543851006
  },
  "Joseph Brito": {
    "archetype": "The Creators (2)",
    "confidence": 0.976358129312692,
    "position": "DM",
    "primary_metric": "Chance Creation (xA/96)",
    "z_score": 2.075345997813466
  },
  "Joseph Farrell": {
    "archetype": "Progressive Carriers",
    "confidence": 0.9957449728368647,
    "position": "CB",
    "primary_metric": "Attacking Directness",
    "z_score": 1.8166004679140146
  },
  "Josh O'brien": {
    "archetype": "Progressive Carriers",
    "confidence": 0.999276883055924,
    "position": "CB",
    "primary_metric": "Attacking Directness",
    "z_score": 1.8353144000506547
  },
  "Josh P\u00e9rez": {
    "archetype": "The Creators (2)",
    "confidence": 0.9996420301763812,
    "position": "AM",
    "primary_metric": "Chance Creation (xA/96)",
    "z_score": 2.465677291435038
  },
  "Joshua Drack": {
    "archetype": "The Finishers (2)",
    "confidence": 0.9707537123897867,
    "position": "FB",
    "primary_metric": "Shot Quality (xG/96)",
    "z_score": -0.669030776973258
  },
  "Jos\u00e9 Hern\u00e1ndez": {
    "archetype": "The Finishers (2)",
    "confidence": 0.963654271929412,
    "position": "CM",
    "primary_metric": "Shot Quality (xG/96)",
    "z_score": -0.8586205287795706
  },
  "Jos\u00e9 Sinisterra": {
    "archetype": "The Finishers (2)",
    "confidence": 0.97118664161757,
    "position": "W",
    "primary_metric": "Shot Quality (xG/96)",
    "z_score": -0.5572721540287139
  },
  "Juan Agudelo": {
    "archetype": "The Creators",
    "confidence": 0.9999993244419593,
    "position": "ST",
    "primary_metric": "Pass Quality Above Model",
    "z_score": -1.1974769012109305
  },
  "Juan Az\u00f3car": {
    "archetype": "The Creators",
    "confidence": 0.9967233099549482,
    "position": "FB",
    "primary_metric": "Pass Quality Above Model",
    "z_score": -0.4937673556586437
  },
  "Juan Sebasti\u00e1n Herrera": {
    "archetype": "The Creators",
    "confidence": 0.9998574526726945,
    "position": "ST",
    "primary_metric": "Pass Quality Above Model",
    "z_score": -1.2470952969907012
  },
  "Juan Tejada": {
    "archetype": "The Finishers",
    "confidence": 0.9930922966016887,
    "position": "W",
    "primary_metric": "Shot Quality (xG/96)",
    "z_score": 1.0752044639568081
  },
  "Juan Torres": {
    "archetype": "The Creators (2)",
    "confidence": 1.0,
    "position": "W",
    "primary_metric": "Chance Creation (xA/96)",
    "z_score": 2.9556564267702163
  },
  "Junior Palacios": {
    "archetype": "Progressive Carriers",
    "confidence": 0.9997490276950393,
    "position": "CB",
    "primary_metric": "Attacking Directness",
    "z_score": 1.4654283330554827
  },
  "Justin Dhillon": {
    "archetype": "The Finishers",
    "confidence": 0.999978926587848,
    "position": "ST",
    "primary_metric": "Shot Quality (xG/96)",
    "z_score": 1.5723210318141132
  },
  "Justin Malou": {
    "archetype": "Progressive Carriers",
    "confidence": 0.9354446537697417,
    "position": "CB",
    "primary_metric": "Attacking Directness",
    "z_score": 1.1680847446622025
  },
  "Justin Portillo": {
    "archetype": "The Finishers (2)",
    "confidence": 0.9296241069293688,
    "position": "DM",
    "primary_metric": "Shot Quality (xG/96)",
    "z_score": -0.6649465847741779
  },
  "Justin Rasmussen": {
    "archetype": "The Finishers (2)",
    "confidence": 0.9956886377671212,
    "position": "FB",
    "primary_metric": "Shot Quality (xG/96)",
    "z_score": -0.7178748952895859
  },
  "Kai Greene": {
    "archetype": "Progressive Carriers",
    "confidence": 0.9635264821375878,
    "position": "CB",
    "primary_metric": "Attacking Directness",
    "z_score": 1.1919969912812423
  },
  "Kalen Ryden": {
    "archetype": "Progressive Carriers",
    "confidence": 0.997664971594502,
    "position": "CB",
    "primary_metric": "Attacking Directness",
    "z_score": 1.0945545863086543
  },
  "Kalil ElMedkhar": {
    "archetype": "The Creators (2)",
    "confidence": 0.9999591070550614,
    "position": "W",
    "primary_metric": "Chance Creation (xA/96)",
    "z_score": 2.1446366315734675
  },
  "Kameron Lacey": {
    "archetype": "The Creators",
    "confidence": 0.9999984989115931,
    "position": "ST",
    "primary_metric": "Pass Quality Above Model",
    "z_score": -3.0956487473319108
  },
  "Karifa Yao": {
    "archetype": "Progressive Carriers",
    "confidence": 0.9999955640872707,
    "position": "CB",
    "primary_metric": "Attacking Directness",
    "z_score": 1.25798959363531
  },
  "Kazaiah Sterling": {
    "archetype": "The Creators",
    "confidence": 0.9999999606969138,
    "position": "ST",
    "primary_metric": "Pass Quality Above Model",
    "z_score": -1.7031487009043627
  },
  "Keegan Hughes": {
    "archetype": "Progressive Carriers",
    "confidence": 0.9790486960126307,
    "position": "CB",
    "primary_metric": "Attacking Directness",
    "z_score": 0.7305686062510061
  },
  "Keegan Tingey": {
    "archetype": "The Finishers (2)",
    "confidence": 0.9747588737257481,
    "position": "FB",
    "primary_metric": "Shot Quality (xG/96)",
    "z_score": -0.3719002330378431
  },
  "Kenardo Forbes": {
    "archetype": "The Creators (2)",
    "confidence": 0.6557318629472345,
    "position": "CM",
    "primary_metric": "Chance Creation (xA/96)",
    "z_score": 0.8176594978242163
  },
  "Kendall Burks": {
    "archetype": "Progressive Carriers",
    "confidence": 0.9999793580149041,
    "position": "CB",
    "primary_metric": "Attacking Directness",
    "z_score": 1.4813091837992145
  },
  "Kevin Partida": {
    "archetype": "The Finishers (2)",
    "confidence": 0.976631776978594,
    "position": "DM",
    "primary_metric": "Shot Quality (xG/96)",
    "z_score": -1.0028942485287107
  },
  "Kevon Lambert": {
    "archetype": "The Finishers (2)",
    "confidence": 0.9995155547180182,
    "position": "DM",
    "primary_metric": "Shot Quality (xG/96)",
    "z_score": -0.3331644350971482
  },
  "Khori Bennett": {
    "archetype": "The Finishers",
    "confidence": 0.9999053086430374,
    "position": "ST",
    "primary_metric": "Shot Quality (xG/96)",
    "z_score": 2.845964212914317
  },
  "Kieran Phillips": {
    "archetype": "The Creators",
    "confidence": 0.9989717525629103,
    "position": "ST",
    "primary_metric": "Pass Quality Above Model",
    "z_score": -0.3989895145306631
  },
  "Koa Santos": {
    "archetype": "The Finishers (2)",
    "confidence": 0.9999589253267597,
    "position": "FB",
    "primary_metric": "Shot Quality (xG/96)",
    "z_score": -0.8478714768904029
  },
  "Kobe Hernandez-Foster": {
    "archetype": "The Creators (2)",
    "confidence": 0.9999687871149449,
    "position": "DM",
    "primary_metric": "Chance Creation (xA/96)",
    "z_score": 0.5539766368551875
  },
  "Kwame Awuah": {
    "archetype": "The Finishers (2)",
    "confidence": 0.9914458072250341,
    "position": "FB",
    "primary_metric": "Shot Quality (xG/96)",
    "z_score": -0.699406146556978
  },
  "Kyle Adams": {
    "archetype": "Progressive Carriers",
    "confidence": 0.9966746080419787,
    "position": "CB",
    "primary_metric": "Attacking Directness",
    "z_score": 1.3021232835908862
  },
  "Kyle Edwards": {
    "archetype": "The Finishers",
    "confidence": 0.9777151373879159,
    "position": "W",
    "primary_metric": "Shot Quality (xG/96)",
    "z_score": 2.215478181933338
  },
  "Kyle Scott": {
    "archetype": "Progressive Carriers",
    "confidence": 0.9999994919817585,
    "position": "CM",
    "primary_metric": "Attacking Directness",
    "z_score": 0.3060222624733978
  },
  "Lamar Batista": {
    "archetype": "Progressive Carriers",
    "confidence": 0.9985750692320502,
    "position": "CB",
    "primary_metric": "Attacking Directness",
    "z_score": 1.7239405122652343
  },
  "Langston Blackstock": {
    "archetype": "The Finishers (2)",
    "confidence": 0.7262566507469777,
    "position": "FB",
    "primary_metric": "Shot Quality (xG/96)",
    "z_score": -0.5893603719772842
  },
  "Laurence Wootton": {
    "archetype": "The Finishers (2)",
    "confidence": 0.9982271280265523,
    "position": "CM",
    "primary_metric": "Shot Quality (xG/96)",
    "z_score": -0.7184065555883167
  },
  "Laurence Wyke": {
    "archetype": "Progressive Carriers",
    "confidence": 0.9999999998967954,
    "position": "FB",
    "primary_metric": "Attacking Directness",
    "z_score": 0.23272602827155778
  },
  "Lee Desmond": {
    "archetype": "Progressive Carriers",
    "confidence": 0.9999543275158158,
    "position": "CB",
    "primary_metric": "Attacking Directness",
    "z_score": 1.2585614082283743
  },
  "Leland Archer": {
    "archetype": "Progressive Carriers",
    "confidence": 0.9995656164093588,
    "position": "CB",
    "primary_metric": "Attacking Directness",
    "z_score": 1.3865958939298866
  },
  "Leo Fernandes": {
    "archetype": "The Creators (2)",
    "confidence": 0.8105135164071883,
    "position": "AM",
    "primary_metric": "Chance Creation (xA/96)",
    "z_score": 1.2874710202721393
  },
  "Leston Paul": {
    "archetype": "The Finishers (2)",
    "confidence": 0.9723449876923366,
    "position": "DM",
    "primary_metric": "Shot Quality (xG/96)",
    "z_score": -0.8630260618486574
  },
  "Lewis Hilton": {
    "archetype": "The Creators (2)",
    "confidence": 0.9967412042474315,
    "position": "CM",
    "primary_metric": "Chance Creation (xA/96)",
    "z_score": 0.6357233424051797
  },
  "Liam Rose": {
    "archetype": "The Finishers (2)",
    "confidence": 0.9751822500134509,
    "position": "DM",
    "primary_metric": "Shot Quality (xG/96)",
    "z_score": -0.9717366326214568
  },
  "Lindo Mfeka": {
    "archetype": "The Finishers (2)",
    "confidence": 0.9154637570232199,
    "position": "AM",
    "primary_metric": "Shot Quality (xG/96)",
    "z_score": -0.3331484736137069
  },
  "Logan Neidlinger": {
    "archetype": "The Finishers (2)",
    "confidence": 0.7097159246417009,
    "position": "FB",
    "primary_metric": "Shot Quality (xG/96)",
    "z_score": -0.653604720222503
  },
  "Louis P\u00e9rez": {
    "archetype": "The Creators (2)",
    "confidence": 0.9999399750494068,
    "position": "AM",
    "primary_metric": "Chance Creation (xA/96)",
    "z_score": 0.8755738914873249
  },
  "Lucas Silva": {
    "archetype": "The Finishers (2)",
    "confidence": 0.9947634236425135,
    "position": "FB",
    "primary_metric": "Shot Quality (xG/96)",
    "z_score": -0.5074550176428427
  },
  "Lucas Stauffer": {
    "archetype": "The Creators (2)",
    "confidence": 0.7397679440842713,
    "position": "FB",
    "primary_metric": "Chance Creation (xA/96)",
    "z_score": 1.294856723115372
  },
  "Lucas Turci": {
    "archetype": "Progressive Carriers",
    "confidence": 0.9991349618316234,
    "position": "CB",
    "primary_metric": "Attacking Directness",
    "z_score": 2.947779690856667
  },
  "Luis Felipe Fernandes": {
    "archetype": "The Finishers (2)",
    "confidence": 0.9844322968512936,
    "position": "CM",
    "primary_metric": "Shot Quality (xG/96)",
    "z_score": -0.511332910531377
  },
  "Luis Pedro Leite da Silva": {
    "archetype": "The Creators",
    "confidence": 0.9997839422667073,
    "position": "W",
    "primary_metric": "Pass Quality Above Model",
    "z_score": -2.0055191816731135
  },
  "Luis Solignac": {
    "archetype": "The Creators",
    "confidence": 0.9999999999792184,
    "position": "ST",
    "primary_metric": "Pass Quality Above Model",
    "z_score": -2.2318192975605804
  },
  "Luiz Fernando": {
    "archetype": "The Creators (2)",
    "confidence": 0.8309877573319951,
    "position": "W",
    "primary_metric": "Chance Creation (xA/96)",
    "z_score": 0.6547402093849043
  },
  "Luke Biasi": {
    "archetype": "Progressive Carriers",
    "confidence": 0.9999917423690431,
    "position": "CB",
    "primary_metric": "Attacking Directness",
    "z_score": 2.1864085601919507
  },
  "Luke Haakenson": {
    "archetype": "The Finishers (2)",
    "confidence": 0.9988503416856882,
    "position": "CM",
    "primary_metric": "Shot Quality (xG/96)",
    "z_score": -0.5526873294726549
  },
  "Maalique Foster": {
    "archetype": "The Creators (2)",
    "confidence": 0.999998605011887,
    "position": "W",
    "primary_metric": "Chance Creation (xA/96)",
    "z_score": 2.7711697706115377
  },
  "Machop Chol": {
    "archetype": "The Creators",
    "confidence": 0.9952851055704098,
    "position": "ST",
    "primary_metric": "Pass Quality Above Model",
    "z_score": 0.31504602149471117
  },
  "Maliek Howell": {
    "archetype": "Progressive Carriers",
    "confidence": 0.985690546952766,
    "position": "CB",
    "primary_metric": "Attacking Directness",
    "z_score": 0.515852226555474
  },
  "Manuel Arteaga": {
    "archetype": "Box Infiltrators",
    "confidence": 1.0,
    "position": "ST",
    "primary_metric": "Receiving Impact",
    "z_score": 3.693758504959345
  },
  "Manuel Botta": {
    "archetype": "The Finishers (2)",
    "confidence": 0.9952825176949064,
    "position": "CM",
    "primary_metric": "Shot Quality (xG/96)",
    "z_score": -0.5023481600297431
  },
  "Marc Ybarra": {
    "archetype": "The Finishers (2)",
    "confidence": 0.99691389828074,
    "position": "CM",
    "primary_metric": "Shot Quality (xG/96)",
    "z_score": -0.901663464950701
  },
  "Marco Micaletto": {
    "archetype": "The Finishers (2)",
    "confidence": 0.9726006463711525,
    "position": "DM",
    "primary_metric": "Shot Quality (xG/96)",
    "z_score": -0.30267197869597817
  },
  "Marcus Epps": {
    "archetype": "The Finishers (2)",
    "confidence": 0.9468080607696516,
    "position": "W",
    "primary_metric": "Shot Quality (xG/96)",
    "z_score": -0.023929143838953705
  },
  "Mark Doyle": {
    "archetype": "The Creators",
    "confidence": 0.9941684249724277,
    "position": "ST",
    "primary_metric": "Pass Quality Above Model",
    "z_score": 0.22097222517171367
  },
  "Mark Segbers": {
    "archetype": "Progressive Carriers",
    "confidence": 0.9437100359011732,
    "position": "FB",
    "primary_metric": "Attacking Directness",
    "z_score": 0.23010087945794588
  },
  "Markus Nakkim": {
    "archetype": "The Finishers (2)",
    "confidence": 0.8781259983863343,
    "position": "CB",
    "primary_metric": "Shot Quality (xG/96)",
    "z_score": -0.4817806272453987
  },
  "Marlon": {
    "archetype": "The Creators (2)",
    "confidence": 0.9988052251053801,
    "position": "ST",
    "primary_metric": "Chance Creation (xA/96)",
    "z_score": 1.0074632590699557
  },
  "Marlon Hairston": {
    "archetype": "The Finishers (2)",
    "confidence": 0.9697905892054925,
    "position": "DM",
    "primary_metric": "Shot Quality (xG/96)",
    "z_score": -0.46480149339693166
  },
  "Matt Myers": {
    "archetype": "Box Infiltrators",
    "confidence": 1.0,
    "position": "ST",
    "primary_metric": "Receiving Impact",
    "z_score": 3.2561143278711535
  },
  "Matt Real": {
    "archetype": "Progressive Carriers",
    "confidence": 0.9542462871565013,
    "position": "FB",
    "primary_metric": "Attacking Directness",
    "z_score": 1.1110592347902744
  },
  "Matthew Mahoney": {
    "archetype": "Progressive Carriers",
    "confidence": 0.9999998952591388,
    "position": "CB",
    "primary_metric": "Attacking Directness",
    "z_score": 1.7173906360174105
  },
  "Matthew Sheldon": {
    "archetype": "The Finishers (2)",
    "confidence": 0.9999834245938056,
    "position": "FB",
    "primary_metric": "Shot Quality (xG/96)",
    "z_score": -0.4227966734666233
  },
  "Maximiliano Rodr\u00edguez": {
    "archetype": "The Creators",
    "confidence": 0.9982551475091401,
    "position": "AM",
    "primary_metric": "Pass Quality Above Model",
    "z_score": -1.2689206859451814
  },
  "Micael DeShields": {
    "archetype": "Progressive Carriers",
    "confidence": 0.8911439570927727,
    "position": "FB",
    "primary_metric": "Attacking Directness",
    "z_score": 0.67330917222737
  },
  "Michael Bryant": {
    "archetype": "Progressive Carriers",
    "confidence": 0.9991914757394512,
    "position": "FB",
    "primary_metric": "Attacking Directness",
    "z_score": 0.9300019413682823
  },
  "Michael Gonzalez": {
    "archetype": "The Creators",
    "confidence": 0.99960987314265,
    "position": "ST",
    "primary_metric": "Pass Quality Above Model",
    "z_score": -1.5827570392522303
  },
  "Michael Lawrence": {
    "archetype": "The Creators",
    "confidence": 0.9999886495913198,
    "position": "ST",
    "primary_metric": "Pass Quality Above Model",
    "z_score": -1.839465185526354
  },
  "Michael Maldonado": {
    "archetype": "The Creators (2)",
    "confidence": 0.9997155085623396,
    "position": "CM",
    "primary_metric": "Chance Creation (xA/96)",
    "z_score": 0.5966640135940292
  },
  "Miche-Naider Ch\u00e9ry": {
    "archetype": "The Finishers",
    "confidence": 0.55535831487478,
    "position": "ST",
    "primary_metric": "Shot Quality (xG/96)",
    "z_score": 0.9891244489448289
  },
  "Michee Ngalina": {
    "archetype": "The Creators",
    "confidence": 0.9988039269877503,
    "position": "W",
    "primary_metric": "Pass Quality Above Model",
    "z_score": -0.440930469341807
  },
  "Miguel Perez": {
    "archetype": "The Creators",
    "confidence": 0.9993063320711031,
    "position": "CM",
    "primary_metric": "Pass Quality Above Model",
    "z_score": -0.8143088975845806
  },
  "Miles Lyons": {
    "archetype": "The Finishers (2)",
    "confidence": 0.9867966224331042,
    "position": "FB",
    "primary_metric": "Shot Quality (xG/96)",
    "z_score": -0.8662320815414813
  },
  "Mitchell Taintor": {
    "archetype": "Progressive Carriers",
    "confidence": 0.9995958830423258,
    "position": "CB",
    "primary_metric": "Attacking Directness",
    "z_score": 2.480893075619911
  },
  "Mobi Fehr": {
    "archetype": "The Finishers (2)",
    "confidence": 0.9995164141738866,
    "position": "CM",
    "primary_metric": "Shot Quality (xG/96)",
    "z_score": -0.11509555473401599
  },
  "Mohamed Traore": {
    "archetype": "Progressive Carriers",
    "confidence": 0.9013503713704408,
    "position": "CB",
    "primary_metric": "Attacking Directness",
    "z_score": 1.0803371961992903
  },
  "Morey Doner": {
    "archetype": "The Finishers (2)",
    "confidence": 0.9594627455276887,
    "position": "FB",
    "primary_metric": "Shot Quality (xG/96)",
    "z_score": -0.9382614904511346
  },
  "Morris Duggan": {
    "archetype": "Progressive Carriers",
    "confidence": 0.9770191926674031,
    "position": "CB",
    "primary_metric": "Attacking Directness",
    "z_score": 1.2188462855828384
  },
  "Moses Mensah": {
    "archetype": "The Finishers (2)",
    "confidence": 0.999973799215842,
    "position": "FB",
    "primary_metric": "Shot Quality (xG/96)",
    "z_score": -0.9488748688797825
  },
  "Mujeeb Murana": {
    "archetype": "The Finishers (2)",
    "confidence": 0.9998607799153131,
    "position": "FB",
    "primary_metric": "Shot Quality (xG/96)",
    "z_score": -0.6454995066869343
  },
  "Mukwelle Akale": {
    "archetype": "The Creators (2)",
    "confidence": 0.9999993358538062,
    "position": "W",
    "primary_metric": "Chance Creation (xA/96)",
    "z_score": 1.6048219719687573
  },
  "Napo Matsoso": {
    "archetype": "The Finishers (2)",
    "confidence": 0.9570355613061449,
    "position": "DM",
    "primary_metric": "Shot Quality (xG/96)",
    "z_score": -0.7985639975443165
  },
  "Nathan Dossantos": {
    "archetype": "The Finishers (2)",
    "confidence": 0.6770803796278695,
    "position": "FB",
    "primary_metric": "Shot Quality (xG/96)",
    "z_score": -0.7033444002552743
  },
  "Nathan Worth": {
    "archetype": "The Finishers (2)",
    "confidence": 0.8125960756894135,
    "position": "CM",
    "primary_metric": "Shot Quality (xG/96)",
    "z_score": -0.251753291460711
  },
  "Nelson Blanco": {
    "archetype": "The Finishers (2)",
    "confidence": 0.9997044653906735,
    "position": "FB",
    "primary_metric": "Shot Quality (xG/96)",
    "z_score": -0.901443712178817
  },
  "Neveal Hackshaw": {
    "archetype": "Progressive Carriers",
    "confidence": 0.9674941566108031,
    "position": "CB",
    "primary_metric": "Attacking Directness",
    "z_score": 2.343891497436259
  },
  "Niall Logue": {
    "archetype": "Progressive Carriers",
    "confidence": 0.9995109108534213,
    "position": "CB",
    "primary_metric": "Attacking Directness",
    "z_score": 2.3370297223194907
  },
  "Niall McCabe": {
    "archetype": "The Finishers (2)",
    "confidence": 0.971638312483703,
    "position": "CM",
    "primary_metric": "Shot Quality (xG/96)",
    "z_score": -0.237333041127066
  },
  "Nicholas Hinds": {
    "archetype": "The Creators",
    "confidence": 0.664900126305376,
    "position": "FB",
    "primary_metric": "Pass Quality Above Model",
    "z_score": 0.02598534013445306
  },
  "Nicholas Markanich": {
    "archetype": "Box Infiltrators",
    "confidence": 1.0,
    "position": "W",
    "primary_metric": "Receiving Impact",
    "z_score": 4.227395681702065
  },
  "Nick Moon": {
    "archetype": "The Creators",
    "confidence": 0.9993500274510102,
    "position": "FB",
    "primary_metric": "Pass Quality Above Model",
    "z_score": -0.3444092791729154
  },
  "Nick Ross": {
    "archetype": "The Creators (2)",
    "confidence": 0.9990561806434499,
    "position": "CM",
    "primary_metric": "Chance Creation (xA/96)",
    "z_score": 0.2047103253135498
  },
  "Nicol\u00e1s Cardona": {
    "archetype": "The Finishers (2)",
    "confidence": 0.9688990665672429,
    "position": "CB",
    "primary_metric": "Shot Quality (xG/96)",
    "z_score": -0.5215940882442781
  },
  "Nighte Pickering": {
    "archetype": "The Creators",
    "confidence": 0.9999880199915174,
    "position": "W",
    "primary_metric": "Pass Quality Above Model",
    "z_score": -1.4253862623669307
  },
  "Noah Dollenmayer": {
    "archetype": "Progressive Carriers",
    "confidence": 0.9935946785516538,
    "position": "CB",
    "primary_metric": "Attacking Directness",
    "z_score": 1.5605055049385783
  },
  "Noah Fuson": {
    "archetype": "The Creators (2)",
    "confidence": 0.9999999996833324,
    "position": "ST",
    "primary_metric": "Chance Creation (xA/96)",
    "z_score": 2.1437316438666865
  },
  "Noe Meza": {
    "archetype": "The Finishers",
    "confidence": 0.994645512847115,
    "position": "W",
    "primary_metric": "Shot Quality (xG/96)",
    "z_score": 0.4737934866168981
  },
  "Oalex Anderson": {
    "archetype": "The Creators",
    "confidence": 0.9999957661703568,
    "position": "ST",
    "primary_metric": "Pass Quality Above Model",
    "z_score": -1.279414306133741
  },
  "Oscar Jimenez": {
    "archetype": "The Finishers (2)",
    "confidence": 0.9996432054278607,
    "position": "FB",
    "primary_metric": "Shot Quality (xG/96)",
    "z_score": -0.8656911212285913
  },
  "Ousman Jabang": {
    "archetype": "Progressive Carriers",
    "confidence": 0.9980436500730312,
    "position": "CM",
    "primary_metric": "Attacking Directness",
    "z_score": 0.37313250244118196
  },
  "Owen Damm": {
    "archetype": "The Finishers (2)",
    "confidence": 0.9277492128660914,
    "position": "FB",
    "primary_metric": "Shot Quality (xG/96)",
    "z_score": -0.7325371969554316
  },
  "Owen Lamb": {
    "archetype": "The Finishers (2)",
    "confidence": 0.985734702052574,
    "position": "FB",
    "primary_metric": "Shot Quality (xG/96)",
    "z_score": -0.8112742689868355
  },
  "Pacifique Niyongabire": {
    "archetype": "The Creators (2)",
    "confidence": 0.9999883997996333,
    "position": "FB",
    "primary_metric": "Chance Creation (xA/96)",
    "z_score": 2.1682417269209346
  },
  "Paco Craig": {
    "archetype": "Progressive Carriers",
    "confidence": 0.993392449943965,
    "position": "CB",
    "primary_metric": "Attacking Directness",
    "z_score": 1.8022791115150028
  },
  "Panos Armenakas": {
    "archetype": "The Creators (2)",
    "confidence": 0.9973255433520032,
    "position": "W",
    "primary_metric": "Chance Creation (xA/96)",
    "z_score": 1.7410511552412609
  },
  "Pape Boye": {
    "archetype": "Progressive Carriers",
    "confidence": 0.9870149579855542,
    "position": "CB",
    "primary_metric": "Attacking Directness",
    "z_score": 1.3048004155493225
  },
  "Patrick Hogan": {
    "archetype": "Progressive Carriers",
    "confidence": 0.9999997678641112,
    "position": "CB",
    "primary_metric": "Attacking Directness",
    "z_score": 2.190697169639931
  },
  "Patrick Seagrist": {
    "archetype": "Progressive Carriers",
    "confidence": 0.999933181088551,
    "position": "FB",
    "primary_metric": "Attacking Directness",
    "z_score": 1.4085067894732024
  },
  "Phanuel Kavita": {
    "archetype": "Progressive Carriers",
    "confidence": 0.9986968871794404,
    "position": "CB",
    "primary_metric": "Attacking Directness",
    "z_score": 0.8446456175672742
  },
  "Phillip Goodrum": {
    "archetype": "The Finishers",
    "confidence": 0.9697462368791363,
    "position": "ST",
    "primary_metric": "Shot Quality (xG/96)",
    "z_score": 1.9757076384096075
  },
  "Pierce Gallaway": {
    "archetype": "The Finishers (2)",
    "confidence": 0.9929743353445576,
    "position": "DM",
    "primary_metric": "Shot Quality (xG/96)",
    "z_score": -0.9659627161579687
  },
  "Preston Tabort Etaka": {
    "archetype": "The Creators",
    "confidence": 0.9983560541514853,
    "position": "W",
    "primary_metric": "Pass Quality Above Model",
    "z_score": -1.0006796152465702
  },
  "Prince Saydee": {
    "archetype": "The Creators",
    "confidence": 0.9999054843592186,
    "position": "W",
    "primary_metric": "Pass Quality Above Model",
    "z_score": -1.9873145945728325
  },
  "Prosper Kasim": {
    "archetype": "The Creators (2)",
    "confidence": 0.7071911551780283,
    "position": "W",
    "primary_metric": "Chance Creation (xA/96)",
    "z_score": 1.2271617304220677
  },
  "Quenzi Huerman": {
    "archetype": "The Creators (2)",
    "confidence": 0.961330089963131,
    "position": "W",
    "primary_metric": "Chance Creation (xA/96)",
    "z_score": 1.0426269804887671
  },
  "Rafael Baca": {
    "archetype": "Progressive Carriers",
    "confidence": 0.9869266127126541,
    "position": "DM",
    "primary_metric": "Attacking Directness",
    "z_score": 0.598921291984226
  },
  "Rafael Jauregui": {
    "archetype": "The Creators",
    "confidence": 0.9903518708469964,
    "position": "W",
    "primary_metric": "Pass Quality Above Model",
    "z_score": 0.8787512286846183
  },
  "Rafael Mentzingen": {
    "archetype": "The Creators",
    "confidence": 0.9150763138933967,
    "position": "FB",
    "primary_metric": "Pass Quality Above Model",
    "z_score": -0.43747729720307976
  },
  "Raheem Sommersall": {
    "archetype": "The Finishers (2)",
    "confidence": 0.9691742719516734,
    "position": "CM",
    "primary_metric": "Shot Quality (xG/96)",
    "z_score": -0.8291407902738969
  },
  "Ramiz Hamouda": {
    "archetype": "The Finishers (2)",
    "confidence": 0.9880425267088013,
    "position": "FB",
    "primary_metric": "Shot Quality (xG/96)",
    "z_score": -0.9930088932646415
  },
  "Rashid Tetteh": {
    "archetype": "Progressive Carriers",
    "confidence": 0.9831441407039367,
    "position": "CB",
    "primary_metric": "Attacking Directness",
    "z_score": 1.6707097719654587
  },
  "Ray Serrano": {
    "archetype": "The Creators (2)",
    "confidence": 0.9999999996172981,
    "position": "W",
    "primary_metric": "Chance Creation (xA/96)",
    "z_score": 2.703937451143655
  },
  "Rece Buckmaster": {
    "archetype": "The Finishers (2)",
    "confidence": 0.9956864449583317,
    "position": "FB",
    "primary_metric": "Shot Quality (xG/96)",
    "z_score": -0.9015712649913789
  },
  "Renzo Zambrano": {
    "archetype": "The Creators (2)",
    "confidence": 0.9053104870338354,
    "position": "DM",
    "primary_metric": "Chance Creation (xA/96)",
    "z_score": 0.3431711144790214
  },
  "Rhys Williams": {
    "archetype": "The Finishers (2)",
    "confidence": 0.994294256868421,
    "position": "W",
    "primary_metric": "Shot Quality (xG/96)",
    "z_score": 0.013875011181979641
  },
  "Ricardo Zacarias": {
    "archetype": "The Creators",
    "confidence": 0.9999227776489792,
    "position": "W",
    "primary_metric": "Pass Quality Above Model",
    "z_score": -1.3015749545191655
  },
  "Ricky Ruiz": {
    "archetype": "The Finishers (2)",
    "confidence": 0.9745325453094044,
    "position": "FB",
    "primary_metric": "Shot Quality (xG/96)",
    "z_score": -0.6294037992059394
  },
  "Rida Zouhir": {
    "archetype": "The Finishers (2)",
    "confidence": 0.981155611812244,
    "position": "CM",
    "primary_metric": "Shot Quality (xG/96)",
    "z_score": -0.6300479317051161
  },
  "Riki Alba": {
    "archetype": "The Creators",
    "confidence": 0.9999999999999964,
    "position": "ST",
    "primary_metric": "Pass Quality Above Model",
    "z_score": -3.2950610568576373
  },
  "Riley Bidois": {
    "archetype": "The Creators",
    "confidence": 0.9322112367900163,
    "position": "W",
    "primary_metric": "Pass Quality Above Model",
    "z_score": -0.8902451586934863
  },
  "Robbie Crawford": {
    "archetype": "The Finishers (2)",
    "confidence": 0.9958310188726383,
    "position": "FB",
    "primary_metric": "Shot Quality (xG/96)",
    "z_score": -0.47803320179017494
  },
  "Robbie Mertz": {
    "archetype": "The Creators (2)",
    "confidence": 0.9993816188093088,
    "position": "CM",
    "primary_metric": "Chance Creation (xA/96)",
    "z_score": 1.5511983686379145
  },
  "Robert Coronado": {
    "archetype": "The Finishers (2)",
    "confidence": 0.9828559429511226,
    "position": "CM",
    "primary_metric": "Shot Quality (xG/96)",
    "z_score": 0.02748122842906649
  },
  "Robert Dambrot": {
    "archetype": "The Finishers (2)",
    "confidence": 0.9995432852825397,
    "position": "CB",
    "primary_metric": "Shot Quality (xG/96)",
    "z_score": -0.5240768779666618
  },
  "Roberto Molina": {
    "archetype": "The Creators",
    "confidence": 0.9373228621488807,
    "position": "FB",
    "primary_metric": "Pass Quality Above Model",
    "z_score": -1.5063849408830967
  },
  "Rocco Genzano": {
    "archetype": "The Creators",
    "confidence": 0.9940245851705217,
    "position": "W",
    "primary_metric": "Pass Quality Above Model",
    "z_score": -1.8235068366134008
  },
  "Rodrigo L\u00f3pez": {
    "archetype": "The Finishers (2)",
    "confidence": 0.642831422449847,
    "position": "W",
    "primary_metric": "Shot Quality (xG/96)",
    "z_score": -0.2782214100103828
  },
  "Rodrigo da Costa": {
    "archetype": "The Creators (2)",
    "confidence": 0.8035353743925289,
    "position": "AM",
    "primary_metric": "Chance Creation (xA/96)",
    "z_score": 1.5382482647142064
  },
  "Romario Williams": {
    "archetype": "The Finishers",
    "confidence": 0.9748253078406965,
    "position": "ST",
    "primary_metric": "Shot Quality (xG/96)",
    "z_score": 1.2269219976654069
  },
  "Ronaldo Damus": {
    "archetype": "The Finishers",
    "confidence": 0.9999991677032334,
    "position": "ST",
    "primary_metric": "Shot Quality (xG/96)",
    "z_score": 2.984911416487122
  },
  "Russell Cicerone": {
    "archetype": "The Creators",
    "confidence": 0.8287620514672807,
    "position": "W",
    "primary_metric": "Pass Quality Above Model",
    "z_score": -0.04049660502182064
  },
  "Ryan Doghman": {
    "archetype": "The Finishers (2)",
    "confidence": 0.9999983297679411,
    "position": "FB",
    "primary_metric": "Shot Quality (xG/96)",
    "z_score": -0.4920391485014844
  },
  "Ryan Flood": {
    "archetype": "The Finishers (2)",
    "confidence": 0.9910359113121074,
    "position": "W",
    "primary_metric": "Shot Quality (xG/96)",
    "z_score": -0.35818391836690344
  },
  "Ryan Williams": {
    "archetype": "The Finishers (2)",
    "confidence": 0.9998584198074937,
    "position": "DM",
    "primary_metric": "Shot Quality (xG/96)",
    "z_score": -0.678355334094586
  },
  "R\u00e9mi Cabral": {
    "archetype": "The Finishers",
    "confidence": 0.9999999991729158,
    "position": "ST",
    "primary_metric": "Shot Quality (xG/96)",
    "z_score": 1.9366348950972938
  },
  "Sam Gleadle": {
    "archetype": "The Creators",
    "confidence": 0.9999901835702736,
    "position": "W",
    "primary_metric": "Pass Quality Above Model",
    "z_score": -2.108142093485193
  },
  "Samuel Biek": {
    "archetype": "The Finishers (2)",
    "confidence": 0.9733156616855275,
    "position": "CB",
    "primary_metric": "Shot Quality (xG/96)",
    "z_score": -0.7066532508729951
  },
  "Samuel Careaga": {
    "archetype": "The Creators (2)",
    "confidence": 0.9980700742490398,
    "position": "DM",
    "primary_metric": "Chance Creation (xA/96)",
    "z_score": 0.174202475101524
  },
  "Sean Suber": {
    "archetype": "Progressive Carriers",
    "confidence": 0.9986063126596546,
    "position": "CB",
    "primary_metric": "Attacking Directness",
    "z_score": 2.300563546225455
  },
  "Sean Totsch": {
    "archetype": "The Creators (2)",
    "confidence": 0.9990103222007548,
    "position": "CB",
    "primary_metric": "Chance Creation (xA/96)",
    "z_score": -0.1532040424399284
  },
  "Sebastian Sanchez": {
    "archetype": "The Finishers (2)",
    "confidence": 0.9940991778384832,
    "position": "DM",
    "primary_metric": "Shot Quality (xG/96)",
    "z_score": -0.8148298860743307
  },
  "Sebasti\u00e1n Guenzatti": {
    "archetype": "The Creators",
    "confidence": 0.9984547035386749,
    "position": "AM",
    "primary_metric": "Pass Quality Above Model",
    "z_score": -0.9576658302564043
  },
  "Sergio Chavez": {
    "archetype": "Progressive Carriers",
    "confidence": 0.9623656659593294,
    "position": "CB",
    "primary_metric": "Attacking Directness",
    "z_score": 1.7319459165681306
  },
  "Sergio Rivas": {
    "archetype": "The Creators",
    "confidence": 0.9241792371956902,
    "position": "DM",
    "primary_metric": "Pass Quality Above Model",
    "z_score": 0.42494406295828413
  },
  "Seth Casiple": {
    "archetype": "The Finishers (2)",
    "confidence": 0.8086590170926126,
    "position": "CM",
    "primary_metric": "Shot Quality (xG/96)",
    "z_score": -0.6888571737918437
  },
  "Shaft Brewer": {
    "archetype": "The Finishers (2)",
    "confidence": 0.9181259643454591,
    "position": "FB",
    "primary_metric": "Shot Quality (xG/96)",
    "z_score": -0.8905225285897614
  },
  "Shane Wiedt": {
    "archetype": "The Finishers (2)",
    "confidence": 0.8018802513124179,
    "position": "CB",
    "primary_metric": "Shot Quality (xG/96)",
    "z_score": -0.09526883978280243
  },
  "Shannon Gomez": {
    "archetype": "The Finishers (2)",
    "confidence": 0.9980020233526771,
    "position": "FB",
    "primary_metric": "Shot Quality (xG/96)",
    "z_score": -0.8474953958983676
  },
  "Shawn Smart": {
    "archetype": "The Finishers (2)",
    "confidence": 0.9598910772704311,
    "position": "FB",
    "primary_metric": "Shot Quality (xG/96)",
    "z_score": -0.14938063897043197
  },
  "Sofiane Djeffal": {
    "archetype": "The Finishers (2)",
    "confidence": 0.9795049652932688,
    "position": "CM",
    "primary_metric": "Shot Quality (xG/96)",
    "z_score": -0.7883125105490411
  },
  "Solomon Asante": {
    "archetype": "The Creators (2)",
    "confidence": 0.9389491125302265,
    "position": "W",
    "primary_metric": "Chance Creation (xA/96)",
    "z_score": 1.0887481645231911
  },
  "Speedy Williams": {
    "archetype": "Progressive Carriers",
    "confidence": 0.975877867668817,
    "position": "DM",
    "primary_metric": "Attacking Directness",
    "z_score": 0.37105317664822196
  },
  "Stefan Stojanovic": {
    "archetype": "The Finishers",
    "confidence": 0.9996925925900568,
    "position": "ST",
    "primary_metric": "Shot Quality (xG/96)",
    "z_score": 1.1304176341456593
  },
  "Stephen Carroll": {
    "archetype": "Progressive Carriers",
    "confidence": 0.9993329740131166,
    "position": "CB",
    "primary_metric": "Attacking Directness",
    "z_score": 2.5411675320433393
  },
  "Stephen Turnbull": {
    "archetype": "The Creators",
    "confidence": 0.959972359956541,
    "position": "FB",
    "primary_metric": "Pass Quality Above Model",
    "z_score": -0.18814485840973255
  },
  "Steven Echeverria": {
    "archetype": "The Finishers (2)",
    "confidence": 0.9674270165514169,
    "position": "CM",
    "primary_metric": "Shot Quality (xG/96)",
    "z_score": -0.6699989124229688
  },
  "St\u00e9fano Pinho": {
    "archetype": "The Finishers",
    "confidence": 0.9998453963645477,
    "position": "ST",
    "primary_metric": "Shot Quality (xG/96)",
    "z_score": 2.1879656861250223
  },
  "Taylor Davila": {
    "archetype": "The Creators (2)",
    "confidence": 1.0,
    "position": "CM",
    "primary_metric": "Chance Creation (xA/96)",
    "z_score": 1.780774686227266
  },
  "Thomas Amang": {
    "archetype": "The Creators",
    "confidence": 0.9997522180250313,
    "position": "ST",
    "primary_metric": "Pass Quality Above Model",
    "z_score": -1.3633632676422176
  },
  "Thomas Vancaeyezeele": {
    "archetype": "The Finishers (2)",
    "confidence": 0.9723276827093021,
    "position": "CB",
    "primary_metric": "Shot Quality (xG/96)",
    "z_score": -0.37135028806764925
  },
  "Thomas Williamson": {
    "archetype": "The Creators",
    "confidence": 0.9903140221178872,
    "position": "W",
    "primary_metric": "Pass Quality Above Model",
    "z_score": 0.5184814441917706
  },
  "Tommy McCabe": {
    "archetype": "Progressive Carriers",
    "confidence": 0.9999890673874722,
    "position": "CM",
    "primary_metric": "Attacking Directness",
    "z_score": 0.2182487224380738
  },
  "Tom\u00e1s \u00c1ngel": {
    "archetype": "The Finishers",
    "confidence": 0.9999583621598881,
    "position": "ST",
    "primary_metric": "Shot Quality (xG/96)",
    "z_score": 2.36143427199806
  },
  "Tony Alfaro": {
    "archetype": "Progressive Carriers",
    "confidence": 0.9996576759898768,
    "position": "CB",
    "primary_metric": "Attacking Directness",
    "z_score": 1.5901358974882585
  },
  "Trayvon Reid": {
    "archetype": "The Creators",
    "confidence": 0.9990060131779718,
    "position": "W",
    "primary_metric": "Pass Quality Above Model",
    "z_score": -0.68902244824066
  },
  "Trevor Amann": {
    "archetype": "The Creators",
    "confidence": 0.9999999999996696,
    "position": "ST",
    "primary_metric": "Pass Quality Above Model",
    "z_score": -3.527563472217576
  },
  "Tristan Hodge": {
    "archetype": "Progressive Carriers",
    "confidence": 0.9195863847588913,
    "position": "FB",
    "primary_metric": "Attacking Directness",
    "z_score": 0.566587775903698
  },
  "Tristan Trager": {
    "archetype": "The Creators",
    "confidence": 0.9999999869804662,
    "position": "ST",
    "primary_metric": "Pass Quality Above Model",
    "z_score": -0.5881764114125856
  },
  "Trova Boni": {
    "archetype": "Progressive Carriers",
    "confidence": 0.9446378276777947,
    "position": "CB",
    "primary_metric": "Attacking Directness",
    "z_score": 1.6238989500514462
  },
  "Tumi Moshobane": {
    "archetype": "The Creators (2)",
    "confidence": 0.8865421469069137,
    "position": "ST",
    "primary_metric": "Chance Creation (xA/96)",
    "z_score": 1.0646823478067395
  },
  "Tyler Gibson": {
    "archetype": "The Finishers (2)",
    "confidence": 0.9913272409139755,
    "position": "CM",
    "primary_metric": "Shot Quality (xG/96)",
    "z_score": -0.5730426639872388
  },
  "Tyler Pasher": {
    "archetype": "The Creators (2)",
    "confidence": 0.9996240957506128,
    "position": "W",
    "primary_metric": "Chance Creation (xA/96)",
    "z_score": 2.374480232346078
  },
  "Tyreek Magee": {
    "archetype": "The Creators (2)",
    "confidence": 0.9551579726707252,
    "position": "AM",
    "primary_metric": "Chance Creation (xA/96)",
    "z_score": 1.7691025039759658
  },
  "Valentin No\u00ebl": {
    "archetype": "The Creators (2)",
    "confidence": 0.8823426585161217,
    "position": "ST",
    "primary_metric": "Chance Creation (xA/96)",
    "z_score": 0.49172680686460013
  },
  "Victor Bezerra": {
    "archetype": "The Creators",
    "confidence": 0.9999999987115764,
    "position": "ST",
    "primary_metric": "Pass Quality Above Model",
    "z_score": -2.851009940571785
  },
  "Wahab Ackwei": {
    "archetype": "Progressive Carriers",
    "confidence": 0.9847542069991385,
    "position": "CB",
    "primary_metric": "Attacking Directness",
    "z_score": 1.384386610274866
  },
  "Walid Yacoubou": {
    "archetype": "Progressive Carriers",
    "confidence": 0.9966890946926791,
    "position": "CB",
    "primary_metric": "Attacking Directness",
    "z_score": 1.2411990378571585
  },
  "Walmer Martinez": {
    "archetype": "The Finishers (2)",
    "confidence": 0.9999991993541116,
    "position": "W",
    "primary_metric": "Shot Quality (xG/96)",
    "z_score": -0.16870913386465336
  },
  "Wesley Charpie": {
    "archetype": "Progressive Carriers",
    "confidence": 0.9993932955259097,
    "position": "CB",
    "primary_metric": "Attacking Directness",
    "z_score": 1.4198391150448342
  },
  "Wesley Leggett": {
    "archetype": "The Creators",
    "confidence": 0.9999420947970307,
    "position": "W",
    "primary_metric": "Pass Quality Above Model",
    "z_score": -1.5267016623983272
  },
  "Will Seymore": {
    "archetype": "Progressive Carriers",
    "confidence": 0.7550336280502353,
    "position": "FB",
    "primary_metric": "Attacking Directness",
    "z_score": 0.6467197936498941
  },
  "Wilson Harris": {
    "archetype": "The Finishers",
    "confidence": 0.999998974968809,
    "position": "ST",
    "primary_metric": "Shot Quality (xG/96)",
    "z_score": 3.2194136040706955
  },
  "Xavi Gnaulati": {
    "archetype": "The Creators",
    "confidence": 0.7988933863711639,
    "position": "AM",
    "primary_metric": "Pass Quality Above Model",
    "z_score": 0.6947608529823339
  },
  "Yanis Leerman": {
    "archetype": "Progressive Carriers",
    "confidence": 0.9998053022800644,
    "position": "CB",
    "primary_metric": "Attacking Directness",
    "z_score": 0.9808934401509781
  },
  "Yazeed Matthews": {
    "archetype": "The Creators",
    "confidence": 0.999989135082157,
    "position": "ST",
    "primary_metric": "Pass Quality Above Model",
    "z_score": -1.7116642904503505
  },
  "Yosuke Hanya": {
    "archetype": "The Creators",
    "confidence": 0.7668749638112095,
    "position": "W",
    "primary_metric": "Pass Quality Above Model",
    "z_score": -0.1915645046053654
  },
  "Younes Boudadi": {
    "archetype": "The Finishers (2)",
    "confidence": 0.9615297650422225,
    "position": "FB",
    "primary_metric": "Shot Quality (xG/96)",
    "z_score": -0.7363090704112619
  },
  "Zach Duncan": {
    "archetype": "The Finishers (2)",
    "confidence": 0.9997648074486545,
    "position": "DM",
    "primary_metric": "Shot Quality (xG/96)",
    "z_score": -0.7273067159768735
  },
  "Zach Ryan": {
    "archetype": "The Finishers",
    "confidence": 0.9999779884043011,
    "position": "ST",
    "primary_metric": "Shot Quality (xG/96)",
    "z_score": 2.2449319638060476
  },
  "Zachary Herivaux": {
    "archetype": "The Finishers (2)",
    "confidence": 0.8207292012198677,
    "position": "CM",
    "primary_metric": "Shot Quality (xG/96)",
    "z_score": -0.13867986430909182
  },
  "Zachary Zandi": {
    "archetype": "The Finishers (2)",
    "confidence": 0.743616905558754,
    "position": "DM",
    "primary_metric": "Shot Quality (xG/96)",
    "z_score": -0.07024506113465574
  },
  "Zico Bailey": {
    "archetype": "The Finishers (2)",
    "confidence": 0.9962326250411925,
    "position": "DM",
    "primary_metric": "Shot Quality (xG/96)",
    "z_score": -0.49283915909723114
  },
  "\u00c1lvaro Quezada": {
    "archetype": "The Finishers (2)",
    "confidence": 0.9999844612385859,
    "position": "FB",
    "primary_metric": "Shot Quality (xG/96)",
    "z_score": -0.6828498629360966
  }
}