{"FC Tucson": {"identity": "Tiki-Taka Purists", "metric": "Possession Quality", "z_score": 1.0540064325534475}, "Richmond Kickers": {"identity": "Vertical Threats", "metric": "Attacking Directness", "z_score": 1.644328404548311}, "Greenville Triumph SC": {"identity": "Vertical Threats", "metric": "Attacking Directness", "z_score": 0.1893105509067687}, "Forward Madison FC": {"identity": "Air Superiority", "metric": "Claiming Impact", "z_score": 0.8905872580008057}, "South Georgia Tormenta FC": {"identity": "Air Superiority", "metric": "Claiming Impact", "z_score": 0.6256594609267107}, "Union Omaha": {"identity": "Vertical Threats", "metric": "Attacking Directness", "z_score": 1.8905870465551422}, "New England Revolution II": {"identity": "Air Superiority", "metric": "Claiming Impact", "z_score": 0.8813650878494924}, "Orlando City B": {"identity": "Open Defenses", "metric": "Defensive Vulnerability (xGA)", "z_score": 1.8618298900323795}, "North Texas SC": {"identity": "Tiki-Taka Purists", "metric": "Possession Quality", "z_score": 0.9446284065337528}, "Chattanooga Red Wolves SC": {"identity": "Air Superiority", "metric": "Claiming Impact", "z_score": 0.4864885295523443}, "Fort Lauderdale CF": {"identity": "Tiki-Taka Purists", "metric": "Possession Quality", "z_score": 1.4634728889348807}}