{
  "Birmingham Legion FC": {
    "explanation": "Birmingham Legion FC is classified under High-Disruption Defense primarily due to its above-average Defensive Disruption (g+) (Z-score: +2.1) and below-average Opponent Directness (Z-score: -1.3).",
    "hybrid_flag": true,
    "hybrid_margin": 0.028181801917007955,
    "identity": "High-Disruption Defense",
    "metric": "Defensive Disruption (g+)",
    "primary_cluster_id": 0,
    "primary_identity": "High-Disruption Defense",
    "scores": {
      "Advanced Receiving": 0.16338699111543367,
      "Direct Attacking": 0.14662767419643405,
      "High-Disruption Defense": 0.1826202169124712,
      "High-Efficiency Passing": 0.17562259224382806,
      "High-Line Pressing": 0.1478448539794372,
      "Possession Dominant": 0.17747365010522112
    },
    "secondary_identity": "Possession Dominant",
    "trait_scores": {
      "attempted_passes_for": 0.48776947298086143,
      "avg_vertical_distance_against": -1.3226547892110296,
      "avg_vertical_distance_for": -0.6684590699968852,
      "claiming": -3.719498970637293,
      "dribbling": 0.49619328746042374,
      "interrupting": 2.104443829554586,
      "pass_completion_percentage_for": 0.7568276323124924,
      "passing": 0.2887078569416409,
      "receiving": -0.15761852594164907
    },
    "z_score": 2.104443829554586
  },
  "Charleston Battery": {
    "explanation": "Charleston Battery is classified under Advanced Receiving primarily due to its above-average Receiving Impact (g+) (Z-score: +1.1) and above-average Opponent Directness (Z-score: +1.2).",
    "hybrid_flag": false,
    "hybrid_margin": 0.10217608297528474,
    "identity": "Advanced Receiving",
    "metric": "Receiving Impact (g+)",
    "primary_cluster_id": 1,
    "primary_identity": "Advanced Receiving",
    "scores": {
      "Advanced Receiving": 0.2948065070617748,
      "Direct Attacking": 0.16542102554966553,
      "High-Disruption Defense": 0.2165812732308779,
      "High-Efficiency Passing": 0.2631875181522714,
      "High-Line Pressing": 0.18033218879399923,
      "Possession Dominant": 0.26468433283240095
    },
    "secondary_identity": "Possession Dominant",
    "trait_scores": {
      "attempted_passes_for": 1.678715488412545,
      "avg_vertical_distance_against": 1.223196662865641,
      "avg_vertical_distance_for": -1.229857407187566,
      "claiming": 0.1656974800478359,
      "dribbling": 0.366401081567241,
      "interrupting": 0.32502561695110177,
      "pass_completion_percentage_for": 1.2179148894697922,
      "passing": 0.9867265744770638,
      "receiving": 1.1479904832017505
    },
    "z_score": 1.1479904832017505
  },
  "Colorado Springs Switchbacks FC": {
    "explanation": "Colorado Springs Switchbacks FC is classified under High-Line Pressing primarily due to its below-average Defensive Disruption (g+) (Z-score: -0.9) and above-average Dribbling Impact (g+) (Z-score: +0.7).",
    "hybrid_flag": false,
    "hybrid_margin": 0.05468215887389871,
    "identity": "High-Line Pressing",
    "metric": "Defensive Disruption (g+)",
    "primary_cluster_id": 5,
    "primary_identity": "High-Line Pressing",
    "scores": {
      "Advanced Receiving": 0.28907378824311086,
      "Direct Attacking": 0.2743154981285857,
      "High-Disruption Defense": 0.3501630463039127,
      "High-Efficiency Passing": 0.38159913668127443,
      "High-Line Pressing": 0.4036728390541959,
      "Possession Dominant": 0.2337290236325266
    },
    "secondary_identity": "High-Efficiency Passing",
    "trait_scores": {
      "attempted_passes_for": -0.28905874338167864,
      "avg_vertical_distance_against": 0.17905362395999058,
      "avg_vertical_distance_for": 0.2642598400388917,
      "claiming": 0.1707271497881295,
      "dribbling": 0.6837894736131124,
      "interrupting": -0.9367030262155881,
      "pass_completion_percentage_for": -0.06420516107728129,
      "passing": 0.153481171592406,
      "receiving": -0.3794866334630528
    },
    "z_score": -0.9367030262155881
  },
  "Detroit City FC": {
    "explanation": "Detroit City FC is classified under High-Disruption Defense primarily due to its above-average Defensive Disruption (g+) (Z-score: +1.2) and below-average Dribbling Impact (g+) (Z-score: -1.0).",
    "hybrid_flag": false,
    "hybrid_margin": 0.07496367317135715,
    "identity": "High-Disruption Defense",
    "metric": "Defensive Disruption (g+)",
    "primary_cluster_id": 0,
    "primary_identity": "High-Disruption Defense",
    "scores": {
      "Advanced Receiving": 0.2106797844332749,
      "Direct Attacking": 0.22068948893492507,
      "High-Disruption Defense": 0.3797566254449368,
      "High-Efficiency Passing": 0.3512886738154614,
      "High-Line Pressing": 0.24628170823656756,
      "Possession Dominant": 0.22187661179386176
    },
    "secondary_identity": "High-Efficiency Passing",
    "trait_scores": {
      "attempted_passes_for": 0.04569262680306334,
      "avg_vertical_distance_against": 0.1667412477001446,
      "avg_vertical_distance_for": -0.4865431220043408,
      "claiming": 0.4333988547182739,
      "dribbling": -1.020550721775996,
      "interrupting": 1.1578995971838473,
      "pass_completion_percentage_for": -0.17427115149547684,
      "passing": 0.36477181841997347,
      "receiving": -1.006009751611245
    },
    "z_score": 1.1578995971838473
  },
  "El Paso Locomotive FC": {
    "explanation": "El Paso Locomotive FC is classified under High-Efficiency Passing primarily due to its above-average Possession Quality (Z-score: +0.7) and above-average Possession Volume (Z-score: +0.6).",
    "hybrid_flag": false,
    "hybrid_margin": 0.18954364321908754,
    "identity": "High-Efficiency Passing",
    "metric": "Possession Quality",
    "primary_cluster_id": 2,
    "primary_identity": "High-Efficiency Passing",
    "scores": {
      "Advanced Receiving": 0.25566977946036157,
      "Direct Attacking": 0.21332873052558135,
      "High-Disruption Defense": 0.3712433708317783,
      "High-Efficiency Passing": 0.45806707284754966,
      "High-Line Pressing": 0.2902396255963325,
      "Possession Dominant": 0.3097137072678639
    },
    "secondary_identity": "High-Disruption Defense",
    "trait_scores": {
      "attempted_passes_for": 0.5766488785786383,
      "avg_vertical_distance_against": 0.4439035437234202,
      "avg_vertical_distance_for": -0.39095731399345746,
      "claiming": 0.3150705115127729,
      "dribbling": -0.3753743575583404,
      "interrupting": -0.11109154332160266,
      "pass_completion_percentage_for": 0.6913829893611341,
      "passing": -0.2982696531702398,
      "receiving": -0.7142602777948379
    },
    "z_score": 0.6913829893611341
  },
  "FC Tulsa": {
    "explanation": "FC Tulsa is classified under Direct Attacking primarily due to its above-average Attacking Directness (Z-score: +1.8) and below-average Possession Quality (Z-score: -1.3).",
    "hybrid_flag": false,
    "hybrid_margin": 0.21374419633396946,
    "identity": "Direct Attacking",
    "metric": "Attacking Directness",
    "primary_cluster_id": 4,
    "primary_identity": "Direct Attacking",
    "scores": {
      "Advanced Receiving": 0.1820551074221769,
      "Direct Attacking": 0.3416441108792898,
      "High-Disruption Defense": 0.2520242789542439,
      "High-Efficiency Passing": 0.21550746989829608,
      "High-Line Pressing": 0.26861966475341825,
      "Possession Dominant": 0.15165109459955436
    },
    "secondary_identity": "High-Line Pressing",
    "trait_scores": {
      "attempted_passes_for": -1.4490342648296717,
      "avg_vertical_distance_against": 0.013238034982279906,
      "avg_vertical_distance_for": 1.7833673909442511,
      "claiming": -0.17778772003336638,
      "dribbling": -1.5466016528862945,
      "interrupting": -0.1306990313715565,
      "pass_completion_percentage_for": -1.3344261856332034,
      "passing": -0.4449963698030928,
      "receiving": -0.5069235509542092
    },
    "z_score": 1.7833673909442511
  },
  "Hartford Athletic": {
    "explanation": "Hartford Athletic is classified under High-Disruption Defense primarily due to its below-average Opponent Directness (Z-score: -0.6) and above-average Defensive Disruption (g+) (Z-score: +0.6).",
    "hybrid_flag": false,
    "hybrid_margin": 0.2397045082664351,
    "identity": "High-Disruption Defense",
    "metric": "Opponent Directness",
    "primary_cluster_id": 0,
    "primary_identity": "High-Disruption Defense",
    "scores": {
      "Advanced Receiving": 0.24414616947691342,
      "Direct Attacking": 0.2599530798728042,
      "High-Disruption Defense": 0.5707585574023256,
      "High-Efficiency Passing": 0.4339451578216368,
      "High-Line Pressing": 0.2904098717739782,
      "Possession Dominant": 0.23876986067197165
    },
    "secondary_identity": "High-Efficiency Passing",
    "trait_scores": {
      "attempted_passes_for": -0.42276486925822715,
      "avg_vertical_distance_against": -0.5859196662713212,
      "avg_vertical_distance_for": 0.21183910201883818,
      "claiming": 0.20775775325846702,
      "dribbling": -0.48882359915641826,
      "interrupting": 0.6491324942913134,
      "pass_completion_percentage_for": 0.11725498528784996,
      "passing": -0.3043803228807557,
      "receiving": 0.1879587189224012
    },
    "z_score": -0.5859196662713212
  },
  "Indy Eleven": {
    "explanation": "Indy Eleven is classified under Direct Attacking primarily due to its below-average Possession Quality (Z-score: -1.9) and above-average Attacking Directness (Z-score: +2.1).",
    "hybrid_flag": false,
    "hybrid_margin": 0.3724128454052236,
    "identity": "Direct Attacking",
    "metric": "Possession Quality",
    "primary_cluster_id": 4,
    "primary_identity": "Direct Attacking",
    "scores": {
      "Advanced Receiving": 0.1903723573392607,
      "Direct Attacking": 0.33327199324941137,
      "High-Disruption Defense": 0.20915722157711475,
      "High-Efficiency Passing": 0.1925750593731773,
      "High-Line Pressing": 0.20890095349391335,
      "Possession Dominant": 0.1367347486207502
    },
    "secondary_identity": "High-Disruption Defense",
    "trait_scores": {
      "attempted_passes_for": -1.1587192320744275,
      "avg_vertical_distance_against": 0.7434154792618516,
      "avg_vertical_distance_for": 2.10512806861469,
      "claiming": 0.3716090047187557,
      "dribbling": -1.6683206377363933,
      "interrupting": 0.2931677010155186,
      "pass_completion_percentage_for": -1.8669075987374422,
      "passing": 0.5957299036273119,
      "receiving": 1.056269689979118
    },
    "z_score": -1.8669075987374422
  },
  "Las Vegas Lights FC": {
    "explanation": "Las Vegas Lights FC is classified under Possession Dominant primarily due to its above-average Possession Volume (Z-score: +2.1) and below-average Attacking Directness (Z-score: -1.7).",
    "hybrid_flag": false,
    "hybrid_margin": 0.34633229404594185,
    "identity": "Possession Dominant",
    "metric": "Possession Volume",
    "primary_cluster_id": 3,
    "primary_identity": "Possession Dominant",
    "scores": {
      "Advanced Receiving": 0.20914225072706857,
      "Direct Attacking": 0.14571767998177904,
      "High-Disruption Defense": 0.19151057649739447,
      "High-Efficiency Passing": 0.21669204805047088,
      "High-Line Pressing": 0.1759565329530934,
      "Possession Dominant": 0.33150184172022257
    },
    "secondary_identity": "High-Efficiency Passing",
    "trait_scores": {
      "attempted_passes_for": 2.074153668246944,
      "avg_vertical_distance_against": 0.8876844097848318,
      "avg_vertical_distance_for": -1.7167896879613183,
      "claiming": -1.177214904081969,
      "dribbling": -0.22503803557641772,
      "interrupting": -0.4625952121285703,
      "pass_completion_percentage_for": 1.7444467895784537,
      "passing": -1.2748398270644548,
      "receiving": 0.16075339889873916
    },
    "z_score": 2.074153668246944
  },
  "Loudoun United FC": {
    "explanation": "Loudoun United FC is classified under Possession Dominant primarily due to its above-average Possession Volume (Z-score: +1.7) and below-average Attacking Directness (Z-score: -1.3).",
    "hybrid_flag": false,
    "hybrid_margin": 0.14511031741139993,
    "identity": "Possession Dominant",
    "metric": "Possession Volume",
    "primary_cluster_id": 3,
    "primary_identity": "Possession Dominant",
    "scores": {
      "Advanced Receiving": 0.21723780151608585,
      "Direct Attacking": 0.15910578465391162,
      "High-Disruption Defense": 0.22856445336808062,
      "High-Efficiency Passing": 0.2629763190029415,
      "High-Line Pressing": 0.18684045907407656,
      "Possession Dominant": 0.3076143325905646
    },
    "secondary_identity": "High-Efficiency Passing",
    "trait_scores": {
      "attempted_passes_for": 1.6943553604844865,
      "avg_vertical_distance_against": -0.7222926163667907,
      "avg_vertical_distance_for": -1.3463946819191452,
      "claiming": 0.8574877259618098,
      "dribbling": -1.0709502303544451,
      "interrupting": -0.963518778035717,
      "pass_completion_percentage_for": 1.1048741425538113,
      "passing": -0.23292434123697567,
      "receiving": 0.7630710201565901
    },
    "z_score": 1.6943553604844865
  },
  "Louisville City FC": {
    "explanation": "Louisville City FC is classified under Advanced Receiving primarily due to its above-average Passing Impact (g+) (Z-score: +2.3) and above-average Receiving Impact (g+) (Z-score: +1.0).",
    "hybrid_flag": false,
    "hybrid_margin": 0.05578439792949407,
    "identity": "Advanced Receiving",
    "metric": "Passing Impact (g+)",
    "primary_cluster_id": 1,
    "primary_identity": "Advanced Receiving",
    "scores": {
      "Advanced Receiving": 0.25965540801897063,
      "Direct Attacking": 0.24517068735771083,
      "High-Disruption Defense": 0.2046135848919286,
      "High-Efficiency Passing": 0.2055191673139135,
      "High-Line Pressing": 0.20410390860243097,
      "Possession Dominant": 0.1559094950884331
    },
    "secondary_identity": "Direct Attacking",
    "trait_scores": {
      "attempted_passes_for": -0.8476951049738942,
      "avg_vertical_distance_against": 0.09915700844772758,
      "avg_vertical_distance_for": 0.7354574851629644,
      "claiming": -0.9857985913255346,
      "dribbling": 1.1310934162248294,
      "interrupting": -1.4032533154322424,
      "pass_completion_percentage_for": -0.9179602759427374,
      "passing": 2.2511649368151327,
      "receiving": 1.0489356404267265
    },
    "z_score": 2.2511649368151327
  },
  "Memphis 901 FC": {
    "explanation": "Memphis 901 FC is classified under High-Efficiency Passing primarily due to its above-average Claiming Impact (g+) (Z-score: +1.1) and above-average Passing Impact (g+) (Z-score: +2.1).",
    "hybrid_flag": false,
    "hybrid_margin": 0.047854009784109065,
    "identity": "High-Efficiency Passing",
    "metric": "Claiming Impact (g+)",
    "primary_cluster_id": 2,
    "primary_identity": "High-Efficiency Passing",
    "scores": {
      "Advanced Receiving": 0.24898828108099225,
      "Direct Attacking": 0.22713180920774775,
      "High-Disruption Defense": 0.25911816385282804,
      "High-Efficiency Passing": 0.27214121212854053,
      "High-Line Pressing": 0.21042749848898626,
      "Possession Dominant": 0.17800893821100958
    },
    "secondary_identity": "High-Disruption Defense",
    "trait_scores": {
      "attempted_passes_for": 0.035754210226456945,
      "avg_vertical_distance_against": 1.019640964047966,
      "avg_vertical_distance_for": 0.4927065554874375,
      "claiming": 1.1096754952037988,
      "dribbling": -0.6837321027220913,
      "interrupting": 0.042504138961994085,
      "pass_completion_percentage_for": 0.11130547229226923,
      "passing": 2.1332773405818277,
      "receiving": 0.17050652349164874
    },
    "z_score": 1.1096754952037988
  },
  "Monterey Bay FC": {
    "explanation": "Monterey Bay FC is classified under High-Efficiency Passing primarily due to its above-average Claiming Impact (g+) (Z-score: +1.4) and above-average Defensive Disruption (g+) (Z-score: +1.6).",
    "hybrid_flag": true,
    "hybrid_margin": 0.008579367537521431,
    "identity": "High-Efficiency Passing",
    "metric": "Claiming Impact (g+)",
    "primary_cluster_id": 2,
    "primary_identity": "High-Efficiency Passing",
    "scores": {
      "Advanced Receiving": 0.18686898966789425,
      "Direct Attacking": 0.18505508515044963,
      "High-Disruption Defense": 0.29984624095969453,
      "High-Efficiency Passing": 0.30244099340914404,
      "High-Line Pressing": 0.22542862021786728,
      "Possession Dominant": 0.24047144992584527
    },
    "secondary_identity": "High-Disruption Defense",
    "trait_scores": {
      "attempted_passes_for": 0.5638604748955044,
      "avg_vertical_distance_against": -0.7779659698895743,
      "avg_vertical_distance_for": -0.25607698807669205,
      "claiming": 1.3585407499564595,
      "dribbling": -0.19225937522876688,
      "interrupting": 1.6056529659410588,
      "pass_completion_percentage_for": 0.11725498528784996,
      "passing": -1.0490343045980903,
      "receiving": -0.31998138905510254
    },
    "z_score": 1.3585407499564595
  },
  "New Mexico United": {
    "explanation": "New Mexico United is classified under Possession Dominant primarily due to its above-average Possession Volume (Z-score: +1.0) and below-average Passing Impact (g+) (Z-score: -1.8).",
    "hybrid_flag": false,
    "hybrid_margin": 0.15233124290091518,
    "identity": "Possession Dominant",
    "metric": "Possession Volume",
    "primary_cluster_id": 3,
    "primary_identity": "Possession Dominant",
    "scores": {
      "Advanced Receiving": 0.21402947917484993,
      "Direct Attacking": 0.16633147089107309,
      "High-Disruption Defense": 0.20913902490067027,
      "High-Efficiency Passing": 0.23951659367923195,
      "High-Line Pressing": 0.23386199737114516,
      "Possession Dominant": 0.28255918579710715
    },
    "secondary_identity": "High-Efficiency Passing",
    "trait_scores": {
      "attempted_passes_for": 0.9984175367170863,
      "avg_vertical_distance_against": 0.8122041901049053,
      "avg_vertical_distance_for": -0.7271063483275065,
      "claiming": -0.19562982105221355,
      "dribbling": 2.0027066431581813,
      "interrupting": -0.3576908874309299,
      "pass_completion_percentage_for": 0.8639188662328993,
      "passing": -1.7651816392747486,
      "receiving": -0.3752594250064007
    },
    "z_score": 0.9984175367170863
  },
  "North Carolina FC": {
    "explanation": "North Carolina FC is classified under High-Disruption Defense primarily due to its below-average Opponent Directness (Z-score: -1.4) and below-average Possession Volume (Z-score: -0.6).",
    "hybrid_flag": false,
    "hybrid_margin": 0.0917025908536653,
    "identity": "High-Disruption Defense",
    "metric": "Opponent Directness",
    "primary_cluster_id": 0,
    "primary_identity": "High-Disruption Defense",
    "scores": {
      "Advanced Receiving": 0.2201811630569183,
      "Direct Attacking": 0.23251910348886135,
      "High-Disruption Defense": 0.38709613746183286,
      "High-Efficiency Passing": 0.3515984186554336,
      "High-Line Pressing": 0.26879264613679865,
      "Possession Dominant": 0.2165110808171371
    },
    "secondary_identity": "High-Efficiency Passing",
    "trait_scores": {
      "attempted_passes_for": -0.5512335188293601,
      "avg_vertical_distance_against": -1.3709674830132512,
      "avg_vertical_distance_for": 0.14402029809562375,
      "claiming": 0.7870794071695041,
      "dribbling": 0.3099498466605586,
      "interrupting": -0.17508675505870883,
      "pass_completion_percentage_for": -0.08205370006401687,
      "passing": 0.64733604835348,
      "receiving": -0.35602644628463115
    },
    "z_score": -1.3709674830132512
  },
  "Oakland Roots SC": {
    "explanation": "Oakland Roots SC is classified under High-Line Pressing primarily due to its below-average Passing Impact (g+) (Z-score: -0.6) and below-average Possession Volume (Z-score: -0.7).",
    "hybrid_flag": true,
    "hybrid_margin": 0.014201319946746897,
    "identity": "High-Line Pressing",
    "metric": "Passing Impact (g+)",
    "primary_cluster_id": 5,
    "primary_identity": "High-Line Pressing",
    "scores": {
      "Advanced Receiving": 0.23478178626944973,
      "Direct Attacking": 0.30163183132056504,
      "High-Disruption Defense": 0.4014564651202999,
      "High-Efficiency Passing": 0.335497574758706,
      "High-Line Pressing": 0.4072398079421393,
      "Possession Dominant": 0.21741591855003492
    },
    "secondary_identity": "High-Disruption Defense",
    "trait_scores": {
      "attempted_passes_for": -0.7332307723884651,
      "avg_vertical_distance_against": -0.2960435034579869,
      "avg_vertical_distance_for": 0.426654742733438,
      "claiming": -0.4665342980354456,
      "dribbling": -0.3657162010274399,
      "interrupting": -0.4097520416863779,
      "pass_completion_percentage_for": -0.36168081085618553,
      "passing": -0.6389745590232409,
      "receiving": -0.5783491928964742
    },
    "z_score": -0.6389745590232409
  },
  "Orange County SC": {
    "explanation": "Orange County SC is classified under High-Disruption Defense primarily due to its below-average Opponent Directness (Z-score: -1.8) and below-average Receiving Impact (g+) (Z-score: -0.9).",
    "hybrid_flag": false,
    "hybrid_margin": 0.148175348396627,
    "identity": "High-Disruption Defense",
    "metric": "Opponent Directness",
    "primary_cluster_id": 0,
    "primary_identity": "High-Disruption Defense",
    "scores": {
      "Advanced Receiving": 0.18829981096061812,
      "Direct Attacking": 0.19554472089336994,
      "High-Disruption Defense": 0.3753138332144195,
      "High-Efficiency Passing": 0.319701575071624,
      "High-Line Pressing": 0.24121839846581147,
      "Possession Dominant": 0.24697818325018364
    },
    "secondary_identity": "High-Efficiency Passing",
    "trait_scores": {
      "attempted_passes_for": -0.1972982076558743,
      "avg_vertical_distance_against": -1.7624207499703173,
      "avg_vertical_distance_for": -0.16335202291120493,
      "claiming": 0.25989657822848833,
      "dribbling": -0.3756851433396193,
      "interrupting": 0.5540942324814907,
      "pass_completion_percentage_for": 0.45935198253358817,
      "passing": -0.6477061616354679,
      "receiving": -0.8521413790225797
    },
    "z_score": -1.7624207499703173
  },
  "Phoenix Rising FC": {
    "explanation": "Phoenix Rising FC is classified under Possession Dominant primarily due to its above-average Possession Quality (Z-score: +1.5) and below-average Attacking Directness (Z-score: -1.3).",
    "hybrid_flag": false,
    "hybrid_margin": 0.08523501615574482,
    "identity": "Possession Dominant",
    "metric": "Possession Quality",
    "primary_cluster_id": 3,
    "primary_identity": "Possession Dominant",
    "scores": {
      "Advanced Receiving": 0.2304981489263376,
      "Direct Attacking": 0.1698192640563969,
      "High-Disruption Defense": 0.27227287375497955,
      "High-Efficiency Passing": 0.32385338572792083,
      "High-Line Pressing": 0.20688878151896567,
      "Possession Dominant": 0.3540290583185397
    },
    "secondary_identity": "High-Efficiency Passing",
    "trait_scores": {
      "attempted_passes_for": 1.0712129873016392,
      "avg_vertical_distance_against": 0.10986342258672425,
      "avg_vertical_distance_for": -1.3303234765229492,
      "claiming": 0.361752955025581,
      "dribbling": -0.9030609098375414,
      "interrupting": -0.3506373378706647,
      "pass_completion_percentage_for": 1.5064662697553304,
      "passing": -0.009818794595702465,
      "receiving": -0.24521551867009098
    },
    "z_score": 1.5064662697553304
  },
  "Pittsburgh Riverhounds SC": {
    "explanation": "Pittsburgh Riverhounds SC is classified under Direct Attacking primarily due to its below-average Possession Quality (Z-score: -1.7) and above-average Attacking Directness (Z-score: +1.4).",
    "hybrid_flag": false,
    "hybrid_margin": 0.24703302177507055,
    "identity": "Direct Attacking",
    "metric": "Possession Quality",
    "primary_cluster_id": 4,
    "primary_identity": "Direct Attacking",
    "scores": {
      "Advanced Receiving": 0.23348959097578692,
      "Direct Attacking": 0.35386204776452296,
      "High-Disruption Defense": 0.22984556042886808,
      "High-Efficiency Passing": 0.2169740388866461,
      "High-Line Pressing": 0.26644643656670547,
      "Possession Dominant": 0.16071204001319714
    },
    "secondary_identity": "High-Line Pressing",
    "trait_scores": {
      "attempted_passes_for": -0.47234733725254646,
      "avg_vertical_distance_against": -0.1267483298851021,
      "avg_vertical_distance_for": 1.414991803381182,
      "claiming": -0.8933770655167801,
      "dribbling": -0.5048345722404111,
      "interrupting": -1.6782431042076649,
      "pass_completion_percentage_for": -1.6854474523723078,
      "passing": 0.444720167630061,
      "receiving": 0.4257711650932653
    },
    "z_score": -1.6854474523723078
  },
  "Rhode Island FC": {
    "explanation": "Rhode Island FC is classified under High-Line Pressing primarily due to its below-average Possession Quality (Z-score: -0.8) and above-average Opponent Directness (Z-score: +0.8).",
    "hybrid_flag": false,
    "hybrid_margin": 0.12901656766571584,
    "identity": "High-Line Pressing",
    "metric": "Possession Quality",
    "primary_cluster_id": 5,
    "primary_identity": "High-Line Pressing",
    "scores": {
      "Advanced Receiving": 0.315205084060977,
      "Direct Attacking": 0.32161862174112105,
      "High-Disruption Defense": 0.29486516615870945,
      "High-Efficiency Passing": 0.31950997949291404,
      "High-Line Pressing": 0.3692591729422244,
      "Possession Dominant": 0.2061713102720572
    },
    "secondary_identity": "Direct Attacking",
    "trait_scores": {
      "attempted_passes_for": -0.418928348153287,
      "avg_vertical_distance_against": 0.7626870247120459,
      "avg_vertical_distance_for": 0.28352845802700105,
      "claiming": 0.4853127035070199,
      "dribbling": 0.5343649785458908,
      "interrupting": -0.35277730072117286,
      "pass_completion_percentage_for": -0.8257428245112775,
      "passing": -0.3212697157374757,
      "receiving": 0.8842574186754755
    },
    "z_score": -0.8257428245112775
  },
  "Sacramento Republic FC": {
    "explanation": "Sacramento Republic FC is classified under Advanced Receiving primarily due to its below-average Defensive Disruption (g+) (Z-score: -1.1) and above-average Dribbling Impact (g+) (Z-score: +1.3).",
    "hybrid_flag": true,
    "hybrid_margin": 0.02116700507747607,
    "identity": "Advanced Receiving",
    "metric": "Defensive Disruption (g+)",
    "primary_cluster_id": 1,
    "primary_identity": "Advanced Receiving",
    "scores": {
      "Advanced Receiving": 0.3346586771406191,
      "Direct Attacking": 0.22128005534423,
      "High-Disruption Defense": 0.26713726881136785,
      "High-Efficiency Passing": 0.3275749552011952,
      "High-Line Pressing": 0.2793090501709194,
      "Possession Dominant": 0.24396792964377342
    },
    "secondary_identity": "High-Efficiency Passing",
    "trait_scores": {
      "attempted_passes_for": 0.39353720698428823,
      "avg_vertical_distance_against": 0.5292871964819192,
      "avg_vertical_distance_for": -0.4344589537308052,
      "claiming": 0.4523527964359176,
      "dribbling": 1.2785977349733744,
      "interrupting": -1.1071118456191988,
      "pass_completion_percentage_for": -0.013634300614869884,
      "passing": 0.6700166744598611,
      "receiving": 0.23667067002430248
    },
    "z_score": -1.1071118456191988
  },
  "San Antonio FC": {
    "explanation": "San Antonio FC is classified under Direct Attacking primarily due to its below-average Possession Quality (Z-score: -1.7) and above-average Attacking Directness (Z-score: +1.5).",
    "hybrid_flag": false,
    "hybrid_margin": 0.08259314182361688,
    "identity": "Direct Attacking",
    "metric": "Possession Quality",
    "primary_cluster_id": 4,
    "primary_identity": "Direct Attacking",
    "scores": {
      "Advanced Receiving": 0.18589206984483028,
      "Direct Attacking": 0.3052081513718074,
      "High-Disruption Defense": 0.2101738816767306,
      "High-Efficiency Passing": 0.19975237568659387,
      "High-Line Pressing": 0.28000005115723864,
      "Possession Dominant": 0.14590793554413742
    },
    "secondary_identity": "High-Line Pressing",
    "trait_scores": {
      "attempted_passes_for": -1.5877884447916675,
      "avg_vertical_distance_against": 1.76025716211306,
      "avg_vertical_distance_for": 1.5093996172792548,
      "claiming": -0.007257991461978518,
      "dribbling": 0.6504424864248058,
      "interrupting": 0.7146015645598036,
      "pass_completion_percentage_for": -1.7330435563369337,
      "passing": -0.7600667386921273,
      "receiving": -0.4694533479130655
    },
    "z_score": -1.7330435563369337
  },
  "Tampa Bay Rowdies": {
    "explanation": "Tampa Bay Rowdies is classified under Advanced Receiving primarily due to its above-average Receiving Impact (g+) (Z-score: +2.6) and above-average Dribbling Impact (g+) (Z-score: +2.2).",
    "hybrid_flag": false,
    "hybrid_margin": 0.26696568770266016,
    "identity": "Advanced Receiving",
    "metric": "Receiving Impact (g+)",
    "primary_cluster_id": 1,
    "primary_identity": "Advanced Receiving",
    "scores": {
      "Advanced Receiving": 0.28660665417743014,
      "Direct Attacking": 0.18998242017110603,
      "High-Disruption Defense": 0.18953200500740597,
      "High-Efficiency Passing": 0.2100925113778283,
      "High-Line Pressing": 0.1931116579664406,
      "Possession Dominant": 0.178243814402935
    },
    "secondary_identity": "High-Efficiency Passing",
    "trait_scores": {
      "attempted_passes_for": -0.2552723043527455,
      "avg_vertical_distance_against": 0.5773322299306666,
      "avg_vertical_distance_for": -0.16116431955884303,
      "claiming": 0.35019105057781846,
      "dribbling": 2.175965572410794,
      "interrupting": -0.9342306312592773,
      "pass_completion_percentage_for": 0.010163751367443115,
      "passing": 0.757294575475213,
      "receiving": 2.5951961319557304
    },
    "z_score": 2.5951961319557304
  },
  "The Miami FC": {
    "explanation": "The Miami FC is classified under High-Disruption Defense primarily due to its below-average Opponent Directness (Z-score: -2.4) and below-average Receiving Impact (g+) (Z-score: -2.7).",
    "hybrid_flag": false,
    "hybrid_margin": 0.10169526403560233,
    "identity": "High-Disruption Defense",
    "metric": "Opponent Directness",
    "primary_cluster_id": 0,
    "primary_identity": "High-Disruption Defense",
    "scores": {
      "Advanced Receiving": 0.12984327729737358,
      "Direct Attacking": 0.146017430098691,
      "High-Disruption Defense": 0.20168562038011015,
      "High-Efficiency Passing": 0.18117514786167532,
      "High-Line Pressing": 0.17098852218758162,
      "Possession Dominant": 0.16415899583081509
    },
    "secondary_identity": "High-Efficiency Passing",
    "trait_scores": {
      "attempted_passes_for": -1.2367467636896596,
      "avg_vertical_distance_against": -2.3626490926378176,
      "avg_vertical_distance_for": -0.45986996959285326,
      "claiming": -0.0634508539660514,
      "dribbling": -0.20855698159903652,
      "interrupting": 1.9268686694185586,
      "pass_completion_percentage_for": 0.35821026160876207,
      "passing": -1.5457646406615986,
      "receiving": -2.716655422212404
    },
    "z_score": -2.3626490926378176
  }
}